[{"original_text": "专门骗骗子的骗子是什么骗子！", "username": "沈浩老师", "province": 11, "statuses_count": 14872, "friends_count": 2202, "city": 5, "text": "专门骗骗子的骗子是什么骗子！", "user_description": "数学与头脑相遇的地方 中国传媒大学电视与新闻学院 教授", "mid": "3351827912046064", "verified_reason": "中国传媒大学教授新浪微博社区委员会专家成员", "followers_count": 55086, "parent": "", "t": 1314621511, "gender": "m", "verified": true, "verified_type": 0, "uid": "1657809832"}, {"original_text": "啊哈哈哈 //@沈浩老师:专门骗骗子的骗子是什么骗子！", "username": "zoelyne", "province": 35, "statuses_count": 9206, "friends_count": 213, "city": 1, "text": "啊哈哈哈 ", "user_description": "闭上眼成全漫天黑暗，人人同时亦有些私隐", "mid": "3351829228383186", "verified_reason": "", "followers_count": 962, "parent": "3351827912046064", "t": 1314621825, "gender": "f", "verified": false, "verified_type": 220, "uid": "1699514383"}, {"original_text": "//@沈浩老师: 专门骗骗子的骗子是什么骗子！", "username": "顧從山", "province": 11, "statuses_count": 5136, "friends_count": 630, "city": 5, "text": "", "user_description": "坐看流行坎止，未相迎", "mid": "3351829444649120", "verified_reason": "", "followers_count": 721, "parent": "3351827912046064", "t": 1314621877, "gender": "m", "verified": false, "verified_type": 220, "uid": "1822920451"}, {"original_text": "//@沈浩老师:专门骗骗子的骗子是什么骗子！", "username": "redydidi", "province": 11, "statuses_count": 5318, "friends_count": 1979, "city": 5, "text": "", "user_description": "以天秤座的个性做每一件事，细致，动情，不放纵，不舍弃，完美，坚强 爱南都 爱东早 爱新闻 爱码字 爱憋稿", "mid": "3351837885819561", "verified_reason": "", "followers_count": 4088, "parent": "3351827912046064", "t": 1314623889, "gender": "m", "verified": false, "verified_type": 220, "uid": "1834353725"}]