[{"original_text": "【用GPU+CoreOS+Docker+TensorFlow搭建高效灵活的深度学习研发平台】《Nvidia GPU + CoreOS + Docker + TensorFlow = A Fast, Flexible, Deep Learning Platform》by Mike Orzel & Luke Benson http://t.cn/R4K00KO", "username": "爱可可-爱生活", "province": 11, "statuses_count": 12394, "friends_count": 1272, "city": 5, "text": "【用GPU+CoreOS+Docker+TensorFlow搭建高效灵活的深度学习研发平台】《Nvidia GPU + CoreOS + Docker + TensorFlow = A Fast, Flexible, Deep Learning Platform》by Mike Orzel & Luke Benson http://t.cn/R4K00KO", "user_description": "北邮网络搜索中心老师", "mid": "3929237763783263", "verified_reason": "微博知名互联网帐号 微博签约自媒体", "followers_count": 28905, "parent": "", "t": 1452286747, "gender": "m", "verified": true, "verified_type": 0, "uid": "1402400261"}, {"original_text": "Repost", "username": "山丘15", "province": 400, "statuses_count": 910, "friends_count": 107, "city": 1, "text": "Repost", "user_description": "做一只调戏生活的逗逼 o.O", "mid": "3929239458044539", "verified_reason": "", "followers_count": 75, "parent": "3929237763783263", "t": 1452287151, "gender": "m", "verified": false, "verified_type": -1, "uid": "1726861762"}, {"original_text": "转发微博", "username": "老师木", "province": 11, "statuses_count": 13164, "friends_count": 1369, "city": 1000, "text": "转发微博", "user_description": "", "mid": "3929240833439698", "verified_reason": "", "followers_count": 26566, "parent": "3929237763783263", "t": 1452287478, "gender": "m", "verified": false, "verified_type": -1, "uid": "1991303247"}, {"original_text": "转发微博", "username": "superclocks", "province": 11, "statuses_count": 2131, "friends_count": 225, "city": 8, "text": "转发微博", "user_description": "", "mid": "3929242523788804", "verified_reason": "", "followers_count": 35, "parent": "3929237763783263", "t": 1452287882, "gender": "m", "verified": false, "verified_type": -1, "uid": "2011078613"}, {"original_text": "转发微博", "username": "HappyQQ", "province": 44, "statuses_count": 13911, "friends_count": 2003, "city": 3, "text": "转发微博", "user_description": "软件作者，站长 ( http://www.mama520.cn )，欢迎关注微信公众号：Mobile_Internet", "mid": "3929242977380056", "verified_reason": "", "followers_count": 2454, "parent": "3929237763783263", "t": 1452287990, "gender": "m", "verified": false, "verified_type": 220, "uid": "1653453900"}, {"original_text": "转发微博", "username": "IT布衣", "province": 11, "statuses_count": 703, "friends_count": 305, "city": 1000, "text": "转发微博", "user_description": "跌倒七次，爬起八次！", "mid": "3929243216484498", "verified_reason": "移动终端UI设计师", "followers_count": 193, "parent": "3929237763783263", "t": 1452288047, "gender": "m", "verified": true, "verified_type": 0, "uid": "2033490827"}, {"original_text": "转发微博", "username": "海_大_星", "province": 11, "statuses_count": 5476, "friends_count": 173, "city": 8, "text": "转发微博", "user_description": "", "mid": "3929244369765058", "verified_reason": "", "followers_count": 6, "parent": "3929237763783263", "t": 1452288321, "gender": "m", "verified": false, "verified_type": -1, "uid": "2287952254"}, {"original_text": "mark//@HappyQQ: 转发微博", "username": "阿吉_Aydge", "province": 11, "statuses_count": 28814, "friends_count": 963, "city": 2, "text": "mark", "user_description": "业余互联网观察员/信息安全从业者/前码农/产品经理。微博内容仅代表个人观点，与本人雇主及其他团体无关。", "mid": "3929245606240220", "verified_reason": "", "followers_count": 765, "parent": "3929242977380056", "t": 1452288616, "gender": "m", "verified": false, "verified_type": -1, "uid": "1436183205"}, {"original_text": "@我的印象笔记 ", "username": "Qt超", "province": 11, "statuses_count": 290, "friends_count": 193, "city": 8, "text": "@我的印象笔记 ", "user_description": "所有的高技术工作都要有相应的基础科学作为支撑，为此的结构力学不断努力", "mid": "3929246835507298", "verified_reason": "", "followers_count": 82, "parent": "3929237763783263", "t": 1452288910, "gender": "m", "verified": false, "verified_type": -1, "uid": "2125013635"}, {"original_text": "Repost", "username": "3A狗狗", "province": 100, "statuses_count": 616, "friends_count": 128, "city": 1000, "text": "Repost", "user_description": "", "mid": "3929248094146283", "verified_reason": "", "followers_count": 114, "parent": "3929237763783263", "t": 1452289210, "gender": "m", "verified": false, "verified_type": -1, "uid": "2475016390"}, {"original_text": "//@HappyQQ:转发微博", "username": "Fr0zenW0rld", "province": 23, "statuses_count": 258, "friends_count": 294, "city": 1, "text": "", "user_description": "Mainly:Research in oncology（Basic Meds 7yrs）/Enthusiast of simple lifestyle（K.I.S.S）/Cryptography/Amateur Linux/OpenSUSE User", "mid": "3929248269947516", "verified_reason": "", "followers_count": 326, "parent": "3929242977380056", "t": 1452289251, "gender": "m", "verified": false, "verified_type": -1, "uid": "2151298365"}, {"original_text": "转发微博", "username": "Boyd_CV", "province": 100, "statuses_count": 2437, "friends_count": 87, "city": 1000, "text": "转发微博", "user_description": "北哒...", "mid": "3929248387150581", "verified_reason": "", "followers_count": 54, "parent": "3929237763783263", "t": 1452289280, "gender": "m", "verified": false, "verified_type": -1, "uid": "1046196273"}, {"original_text": " //@老师木:转发微博", "username": "彤言彤趣", "province": 11, "statuses_count": 9878, "friends_count": 927, "city": 5, "text": " ", "user_description": "混东混西，怀揣梦想到处讨饭吃的IT混子～ 想法天马行空，时常想将天上的神马变成自己地球上的座驾～～", "mid": "3929261687389585", "verified_reason": "", "followers_count": 878, "parent": "3929240833439698", "t": 1452292451, "gender": "m", "verified": false, "verified_type": -1, "uid": "1034197953"}, {"original_text": " //@老师木:转发微博", "username": "郑胤THU", "province": 11, "statuses_count": 5064, "friends_count": 1106, "city": 8, "text": " ", "user_description": "清华大学机器学习和深度学习方向博士生，目前正在找工作中。我的个人主页：https://sites.google.com/site/zhengyin1126/ 欢迎大家联系我！", "mid": "3929262333640922", "verified_reason": "", "followers_count": 1749, "parent": "3929240833439698", "t": 1452292605, "gender": "m", "verified": false, "verified_type": 220, "uid": "2034296393"}, {"original_text": "//@老师木:转发微博", "username": "星空下的巫师", "province": 33, "statuses_count": 9119, "friends_count": 924, "city": 1, "text": "", "user_description": "计算机视觉，模式识别，机器学习，深度学习，*Shicai@东南大学，南京，中国~", "mid": "3929263004515401", "verified_reason": "", "followers_count": 4896, "parent": "3929240833439698", "t": 1452292765, "gender": "m", "verified": false, "verified_type": 220, "uid": "1785748853"}, {"original_text": "转发微博", "username": "猫在天_鱼在水", "province": 44, "statuses_count": 1278, "friends_count": 1059, "city": 19, "text": "转发微博", "user_description": "临深渊，履薄冰", "mid": "3929264589738781", "verified_reason": "", "followers_count": 69, "parent": "3929237763783263", "t": 1452293143, "gender": "m", "verified": false, "verified_type": -1, "uid": "1752017505"}, {"original_text": "转发微博", "username": "wht_121", "province": 12, "statuses_count": 13774, "friends_count": 408, "city": 6, "text": "转发微博", "user_description": "资料收集狂", "mid": "3929264808770871", "verified_reason": "", "followers_count": 48, "parent": "3929237763783263", "t": 1452293195, "gender": "m", "verified": false, "verified_type": -1, "uid": "2362412930"}, {"original_text": "转发微博", "username": "Kevin_机器学习_CA", "province": 11, "statuses_count": 5147, "friends_count": 445, "city": 1000, "text": "转发微博", "user_description": "", "mid": "3929265228007300", "verified_reason": "", "followers_count": 1088, "parent": "3929237763783263", "t": 1452293295, "gender": "m", "verified": false, "verified_type": -1, "uid": "2798235231"}, {"original_text": "//@星空下的巫师://@老师木:转发微博", "username": "LightmanLiu", "province": 21, "statuses_count": 3698, "friends_count": 73, "city": 2, "text": "", "user_description": "", "mid": "3929268150935155", "verified_reason": "", "followers_count": 3, "parent": "3929263004515401", "t": 1452293992, "gender": "m", "verified": false, "verified_type": -1, "uid": "5364786900"}, {"original_text": "//@Fr0zenW0rld://@HappyQQ:转发微博", "username": "Frank残念", "province": 400, "statuses_count": 1576, "friends_count": 351, "city": 1, "text": "", "user_description": "高三狗一只 现今拼命复习中", "mid": "3929270223070180", "verified_reason": "", "followers_count": 209, "parent": "3929248269947516", "t": 1452294486, "gender": "m", "verified": false, "verified_type": -1, "uid": "5512911803"}, {"original_text": "转发微博", "username": "达斯丁猫", "province": 51, "statuses_count": 397, "friends_count": 896, "city": 1, "text": "转发微博", "user_description": "", "mid": "3929271133371985", "verified_reason": "", "followers_count": 175, "parent": "3929237763783263", "t": 1452294703, "gender": "m", "verified": false, "verified_type": -1, "uid": "2665480883"}, {"original_text": " //@星空下的巫师://@老师木:转发微博", "username": "austingg", "province": 12, "statuses_count": 529, "friends_count": 254, "city": 4, "text": " ", "user_description": "专注计算机视觉，非真实感渲染，风格化", "mid": "3929271431479326", "verified_reason": "", "followers_count": 135, "parent": "3929263004515401", "t": 1452294774, "gender": "m", "verified": false, "verified_type": -1, "uid": "2100817931"}, {"original_text": "转发微博", "username": "HadXu", "province": 32, "statuses_count": 473, "friends_count": 85, "city": 5, "text": "转发微博", "user_description": "不忘初心 方得始终", "mid": "3929271984629900", "verified_reason": "", "followers_count": 27, "parent": "3929237763783263", "t": 1452294906, "gender": "m", "verified": false, "verified_type": -1, "uid": "3973402612"}, {"original_text": "转发微博", "username": "一座万年的妖精旅店", "province": 41, "statuses_count": 2053, "friends_count": 971, "city": 1, "text": "转发微博", "user_description": "伪文艺萌", "mid": "3929273221714123", "verified_reason": "", "followers_count": 266, "parent": "3929237763783263", "t": 1452295201, "gender": "f", "verified": false, "verified_type": -1, "uid": "2747572575"}, {"original_text": "转发微博", "username": "hbyido", "province": 33, "statuses_count": 53945, "friends_count": 1400, "city": 1, "text": "转发微博", "user_description": "记录时代", "mid": "3929274370849947", "verified_reason": "", "followers_count": 3523, "parent": "3929237763783263", "t": 1452295475, "gender": "m", "verified": false, "verified_type": -1, "uid": "1646706835"}, {"original_text": "//@老师木:转发微博", "username": "BUPT_qixianbiao", "province": 11, "statuses_count": 600, "friends_count": 157, "city": 1, "text": "", "user_description": "", "mid": "3929279870486188", "verified_reason": "", "followers_count": 13, "parent": "3929240833439698", "t": 1452296786, "gender": "m", "verified": false, "verified_type": -1, "uid": "2071038817"}, {"original_text": "@我的印象笔记 ", "username": "幽静_sequ", "province": 100, "statuses_count": 121, "friends_count": 124, "city": 1000, "text": "@我的印象笔记 ", "user_description": "", "mid": "3929280712746899", "verified_reason": "", "followers_count": 20, "parent": "3929237763783263", "t": 1452296987, "gender": "m", "verified": false, "verified_type": -1, "uid": "2922145997"}, {"original_text": "//@老师木:转发微博", "username": "黯眉", "province": 400, "statuses_count": 1285, "friends_count": 222, "city": 2, "text": "", "user_description": "", "mid": "3929281179056952", "verified_reason": "", "followers_count": 33, "parent": "3929240833439698", "t": 1452297098, "gender": "m", "verified": false, "verified_type": -1, "uid": "2339911003"}, {"original_text": "转发微博", "username": "雨中飞鹰0808", "province": 21, "statuses_count": 3081, "friends_count": 396, "city": 2, "text": "转发微博", "user_description": "我不停的努力，只因为坚信幸运就在下一刻眷顾", "mid": "3929281698628041", "verified_reason": "", "followers_count": 186, "parent": "3929237763783263", "t": 1452297221, "gender": "m", "verified": false, "verified_type": -1, "uid": "1818791885"}, {"original_text": "容器是机器学习很不错的选择，包括xgboost，mxnet 都已经可以上docker，比起YARN来是更加干净，不过因为JVM stack一直存在似乎还是YARN用的比较多 //@老师木: 转发微博", "username": "陈天奇怪", "province": 31, "statuses_count": 723, "friends_count": 251, "city": 12, "text": "容器是机器学习很不错的选择，包括xgboost，mxnet 都已经可以上docker，比起YARN来是更加干净，不过因为JVM stack一直存在似乎还是YARN用的比较多 ", "user_description": "想要做研究的coder// http://homes.cs.washington.edu/~tqchen", "mid": "3929282357065057", "verified_reason": "", "followers_count": 11151, "parent": "3929240833439698", "t": 1452297378, "gender": "m", "verified": false, "verified_type": -1, "uid": "2397265244"}, {"original_text": "//@陈天奇怪:容器是机器学习很不错的选择，包括xgboost，mxnet 都已经可以上docker，比起YARN来是更加干净，不过因为JVM stack一直存在似乎还是YARN用的比较多 //@老师木: 转发微博", "username": "砰砰的小屋", "province": 32, "statuses_count": 22378, "friends_count": 1788, "city": 2, "text": "", "user_description": "", "mid": "3929282432423310", "verified_reason": "", "followers_count": 511, "parent": "3929282357065057", "t": 1452297397, "gender": "f", "verified": false, "verified_type": -1, "uid": "2036923815"}, {"original_text": "转发微博", "username": "刘青松_USTC", "province": 31, "statuses_count": 4587, "friends_count": 318, "city": 1, "text": "转发微博", "user_description": "说话人识别/语音识别", "mid": "3929282738998229", "verified_reason": "", "followers_count": 328, "parent": "3929237763783263", "t": 1452297470, "gender": "m", "verified": false, "verified_type": -1, "uid": "1253439973"}, {"original_text": "@我的印象笔记", "username": "绝黛雨儿", "province": 13, "statuses_count": 1067, "friends_count": 743, "city": 7, "text": "@我的印象笔记", "user_description": "做到极致便是道", "mid": "3929283086530433", "verified_reason": "", "followers_count": 114, "parent": "3929237763783263", "t": 1452297553, "gender": "m", "verified": false, "verified_type": -1, "uid": "2793627322"}, {"original_text": "//@陈天奇怪:容器是机器学习很不错的选择，包括xgboost，mxnet 都已经可以上docker，比起YARN来是更加干净，不过因为JVM stack一直存在似乎还是YARN用的比较多 //@老师木: 转发微博", "username": "张德园", "province": 21, "statuses_count": 3468, "friends_count": 200, "city": 1, "text": "", "user_description": "", "mid": "3929283166260491", "verified_reason": "", "followers_count": 262, "parent": "3929282357065057", "t": 1452297572, "gender": "m", "verified": false, "verified_type": -1, "uid": "1994147141"}, {"original_text": "//@陈天奇怪: 容器是机器学习很不错的选择，包括xgboost，mxnet 都已经可以上docker，比起YARN来是更加干净，不过因为JVM stack一直存在似乎还是YARN用的比较多 //@老师木: 转发微博", "username": "爱可可-爱生活", "province": 11, "statuses_count": 12394, "friends_count": 1272, "city": 5, "text": "", "user_description": "北邮网络搜索中心老师", "mid": "3929283258590145", "verified_reason": "微博知名互联网帐号 微博签约自媒体", "followers_count": 28905, "parent": "3929282357065057", "t": 1452297593, "gender": "m", "verified": true, "verified_type": 0, "uid": "1402400261"}, {"original_text": "//@爱可可-爱生活://@陈天奇怪: 容器是机器学习很不错的选择，包括xgboost，mxnet 都已经可以上docker，比起YARN来是更加干净，不过因为JVM stack一直存在似乎还是YARN用的比较多 //@老师木: 转发微博", "username": "AllenIQY", "province": 11, "statuses_count": 2196, "friends_count": 235, "city": 8, "text": "", "user_description": "计算机视觉之深度学习", "mid": "3929284266006867", "verified_reason": "", "followers_count": 27, "parent": "3929283258590145", "t": 1452297834, "gender": "m", "verified": false, "verified_type": -1, "uid": "1660464144"}, {"original_text": "//@hbyido:转发微博", "username": "刘不吃草也能跑", "province": 33, "statuses_count": 1816, "friends_count": 1373, "city": 1, "text": "", "user_description": "年少轻狂，幸福时光~", "mid": "3929284332734813", "verified_reason": "", "followers_count": 365, "parent": "3929274370849947", "t": 1452297850, "gender": "m", "verified": false, "verified_type": 220, "uid": "1846377637"}, {"original_text": " //@老师木:转发微博", "username": "pop0432_Emotion", "province": 100, "statuses_count": 1454, "friends_count": 184, "city": 1000, "text": " ", "user_description": "苦逼程序员啊", "mid": "3929284459028769", "verified_reason": "", "followers_count": 47, "parent": "3929240833439698", "t": 1452297879, "gender": "m", "verified": false, "verified_type": -1, "uid": "2035400661"}, {"original_text": "转发微博", "username": "anch3or", "province": 37, "statuses_count": 7459, "friends_count": 192, "city": 1, "text": "转发微博", "user_description": "若批评不自由，则赞美无意义。", "mid": "3929284462487977", "verified_reason": "", "followers_count": 62, "parent": "3929237763783263", "t": 1452297880, "gender": "m", "verified": false, "verified_type": -1, "uid": "2262061943"}, {"original_text": " //@爱可可-爱生活://@陈天奇怪: 容器是机器学习很不错的选择，包括xgboost，mxnet 都已经可以上docker，比起YARN来是更加干净，不过因为JVM stack一直存在似乎还是YARN用的比较多 //@老师木: 转发微博", "username": "MatrixAssassin", "province": 11, "statuses_count": 227, "friends_count": 210, "city": 5, "text": " ", "user_description": "", "mid": "3929284932485340", "verified_reason": "", "followers_count": 58, "parent": "3929283258590145", "t": 1452297993, "gender": "m", "verified": false, "verified_type": -1, "uid": "1611340403"}, {"original_text": " //@爱可可-爱生活://@陈天奇怪: 容器是机器学习很不错的选择，包括xgboost，mxnet 都已经可以上docker，比起YARN来是更加干净，不过因为JVM stack一直存在似乎还是YARN用的比较多 //@老师木: 转发微博", "username": "superclocks", "province": 11, "statuses_count": 2131, "friends_count": 225, "city": 8, "text": " ", "user_description": "", "mid": "3929284949268947", "verified_reason": "", "followers_count": 35, "parent": "3929283258590145", "t": 1452297997, "gender": "m", "verified": false, "verified_type": -1, "uid": "2011078613"}, {"original_text": " //@爱可可-爱生活://@陈天奇怪: 容器是机器学习很不错的选择，包括xgboost，mxnet 都已经可以上docker，比起YARN来是更加干净，不过因为JVM stack一直存在似乎还是YARN用的比较多 //@老师木: 转发微博", "username": "zaifan2010", "province": 11, "statuses_count": 1835, "friends_count": 429, "city": 8, "text": " ", "user_description": "", "mid": "3929286857634392", "verified_reason": "", "followers_count": 223, "parent": "3929283258590145", "t": 1452298452, "gender": "m", "verified": false, "verified_type": -1, "uid": "1562291757"}, {"original_text": "//@老师木: 转发微博", "username": "SCJustin", "province": 43, "statuses_count": 1392, "friends_count": 325, "city": 1, "text": "", "user_description": "守望心中的梦。", "mid": "3929287356686740", "verified_reason": "", "followers_count": 288, "parent": "3929240833439698", "t": 1452298571, "gender": "m", "verified": false, "verified_type": 220, "uid": "1973127747"}, {"original_text": "//@爱可可-爱生活://@陈天奇怪: 容器是机器学习很不错的选择，包括xgboost，mxnet 都已经可以上docker，比起YARN来是更加干净，不过因为JVM stack一直存在似乎还是YARN用的比较多 //@老师木: 转发微博", "username": "禅系一之花", "province": 100, "statuses_count": 7554, "friends_count": 340, "city": 1000, "text": "", "user_description": "", "mid": "3929287600047791", "verified_reason": "", "followers_count": 138, "parent": "3929283258590145", "t": 1452298629, "gender": "m", "verified": false, "verified_type": -1, "uid": "3977088060"}, {"original_text": "//@爱可可-爱生活: //@陈天奇怪: 容器是机器学习很不错的选择，包括xgboost，mxnet 都已经可以上docker，比起YARN来是更加干净，不过因为JVM stack一直存在似乎还是YARN用的比较多 //@老师木: 转发微博", "username": "RekingWang", "province": 32, "statuses_count": 782, "friends_count": 337, "city": 1, "text": "", "user_description": "吃咸点，看淡点。", "mid": "3929288618810051", "verified_reason": "", "followers_count": 184, "parent": "3929283258590145", "t": 1452298872, "gender": "m", "verified": false, "verified_type": -1, "uid": "1973709903"}, {"original_text": "@mark ", "username": "fly2left", "province": 31, "statuses_count": 1705, "friends_count": 1924, "city": 15, "text": "@mark ", "user_description": "IT男，爱coding,爱linux...", "mid": "3929290355268849", "verified_reason": "", "followers_count": 191, "parent": "3929237763783263", "t": 1452299286, "gender": "m", "verified": false, "verified_type": -1, "uid": "1692120665"}, {"original_text": " //@老师木:转发微博", "username": "zaifan2010", "province": 11, "statuses_count": 1835, "friends_count": 429, "city": 8, "text": " ", "user_description": "", "mid": "3929290724717407", "verified_reason": "", "followers_count": 223, "parent": "3929240833439698", "t": 1452299374, "gender": "m", "verified": false, "verified_type": -1, "uid": "1562291757"}, {"original_text": " //@爱可可-爱生活://@陈天奇怪: 容器是机器学习很不错的选择，包括xgboost，mxnet 都已经可以上docker，比起YARN来是更加干净，不过因为JVM stack一直存在似乎还是YARN用的比较多 //@老师木: 转发微博", "username": "libertywind", "province": 11, "statuses_count": 4141, "friends_count": 176, "city": 1, "text": " ", "user_description": "", "mid": "3929294071615389", "verified_reason": "", "followers_count": 85, "parent": "3929283258590145", "t": 1452300172, "gender": "m", "verified": false, "verified_type": -1, "uid": "2274634757"}, {"original_text": "//@爱可可-爱生活: //@陈天奇怪: 容器是机器学习很不错的选择，包括xgboost，mxnet 都已经可以上docker，比起YARN来是更加干净，不过因为JVM stack一直存在似乎还是YARN用的比较多 //@老师木: 转发微博", "username": "开着奔驰卖西瓜V5", "province": 51, "statuses_count": 2165, "friends_count": 477, "city": 1, "text": "", "user_description": "一句话，一辈子。默默支持，默默关怀。。。", "mid": "3929294390594850", "verified_reason": "", "followers_count": 41, "parent": "3929283258590145", "t": 1452300248, "gender": "m", "verified": false, "verified_type": -1, "uid": "1547606740"}, {"original_text": " //@爱可可-爱生活://@陈天奇怪: 容器是机器学习很不错的选择，包括xgboost，mxnet 都已经可以上docker，比起YARN来是更加干净，不过因为JVM stack一直存在似乎还是YARN用的比较多 //@老师木: 转发微博", "username": "通风大圣猕五哥", "province": 11, "statuses_count": 3214, "friends_count": 205, "city": 14, "text": " ", "user_description": "", "mid": "3929296541861099", "verified_reason": "", "followers_count": 22, "parent": "3929283258590145", "t": 1452300761, "gender": "m", "verified": false, "verified_type": -1, "uid": "1795000297"}, {"original_text": " //@爱可可-爱生活://@陈天奇怪: 容器是机器学习很不错的选择，包括xgboost，mxnet 都已经可以上docker，比起YARN来是更加干净，不过因为JVM stack一直存在似乎还是YARN用的比较多 //@老师木: 转发微博", "username": "周永_52ML", "province": 11, "statuses_count": 3702, "friends_count": 590, "city": 8, "text": " ", "user_description": "计算广告与机器学习- 技术共享平台http://www.52caml.com/", "mid": "3929297582208575", "verified_reason": "", "followers_count": 494, "parent": "3929283258590145", "t": 1452301009, "gender": "m", "verified": false, "verified_type": -1, "uid": "1707438033"}, {"original_text": "//@Kevin_机器学习_CA:转发微博", "username": "檀灵潇_endless", "province": 35, "statuses_count": 521, "friends_count": 229, "city": 1, "text": "", "user_description": "未来的工程师", "mid": "3929297620662377", "verified_reason": "", "followers_count": 147, "parent": "3929265228007300", "t": 1452301018, "gender": "m", "verified": false, "verified_type": -1, "uid": "3608385591"}, {"original_text": "//@老师木:转发微博", "username": "__马卡洛夫", "province": 11, "statuses_count": 1787, "friends_count": 229, "city": 1, "text": "", "user_description": "", "mid": "3929298052148426", "verified_reason": "", "followers_count": 32, "parent": "3929240833439698", "t": 1452301121, "gender": "m", "verified": false, "verified_type": -1, "uid": "3230599814"}, {"original_text": "Repost", "username": "OliviaTheBunny", "province": 400, "statuses_count": 677, "friends_count": 36, "city": 1, "text": "Repost", "user_description": "Hello World!", "mid": "3929298303586229", "verified_reason": "", "followers_count": 35, "parent": "3929237763783263", "t": 1452301181, "gender": "f", "verified": false, "verified_type": -1, "uid": "1434301552"}, {"original_text": "//@McCandless_:转发微博", "username": "Panpan798", "province": 11, "statuses_count": 1887, "friends_count": 2000, "city": 8, "text": "", "user_description": "", "mid": "3929298366837206", "verified_reason": "", "followers_count": 264, "parent": "3929290019787886", "t": 1452301196, "gender": "m", "verified": false, "verified_type": -1, "uid": "2294395253"}, {"original_text": "//@爱可可-爱生活://@陈天奇怪: 容器是机器学习很不错的选择，包括xgboost，mxnet 都已经可以上docker，比起YARN来是更加干净，不过因为JVM stack一直存在似乎还是YARN用的比较多 //@老师木: 转发微博", "username": "qqgeogor", "province": 400, "statuses_count": 12085, "friends_count": 332, "city": 1, "text": "", "user_description": "OLAP，神经网络算法应用与优化，mongodb dba，mysql dba，apache maven，apache axis2，java底层机制", "mid": "3929299118091355", "verified_reason": "", "followers_count": 267, "parent": "3929283258590145", "t": 1452301375, "gender": "m", "verified": false, "verified_type": 220, "uid": "2048202947"}, {"original_text": "//@爱可可-爱生活://@陈天奇怪: 容器是机器学习很不错的选择，包括xgboost，mxnet 都已经可以上docker，比起YARN来是更加干净，不过因为JVM stack一直存在似乎还是YARN用的比较多 //@老师木: 转发微博", "username": "亭林漠漠", "province": 400, "statuses_count": 22353, "friends_count": 1425, "city": 1, "text": "", "user_description": "思路比苦干重要，方向比努力重要！", "mid": "3929301248086460", "verified_reason": "", "followers_count": 369, "parent": "3929283258590145", "t": 1452301883, "gender": "f", "verified": false, "verified_type": -1, "uid": "1645815691"}, {"original_text": " //@陈天奇怪:容器是机器学习很不错的选择，包括xgboost，mxnet 都已经可以上docker，比起YARN来是更加干净，不过因为JVM stack一直存在似乎还是YARN用的比较多 //@老师木: 转发微博", "username": "李武军nju", "province": 32, "statuses_count": 2074, "friends_count": 473, "city": 1, "text": " ", "user_description": "南京大学计算机科学与技术系教师。研究机器学习、数据挖掘、大数据。 http://cs.nju.edu.cn/lwj", "mid": "3929301667332319", "verified_reason": "", "followers_count": 6388, "parent": "3929282357065057", "t": 1452301983, "gender": "m", "verified": false, "verified_type": -1, "uid": "2309457710"}, {"original_text": " //@星空下的巫师://@老师木:转发微博", "username": "梁大为_", "province": 11, "statuses_count": 1686, "friends_count": 282, "city": 8, "text": " ", "user_description": "L V 爱好者(Learning for Vision)", "mid": "3929302779425344", "verified_reason": "", "followers_count": 57, "parent": "3929263004515401", "t": 1452302248, "gender": "m", "verified": false, "verified_type": -1, "uid": "1451731745"}, {"original_text": "//@李武军nju: //@陈天奇怪:容器是机器学习很不错的选择，包括xgboost，mxnet 都已经可以上docker，比起YARN来是更加干净，不过因为JVM stack一直存在似乎还是YARN用的比较多 //@老师木: 转发微博", "username": "穿山岩羊", "province": 11, "statuses_count": 2115, "friends_count": 162, "city": 8, "text": "", "user_description": "一身转战三千里，一剑曾当百万师", "mid": "3929303110310215", "verified_reason": "", "followers_count": 12, "parent": "3929301667332319", "t": 1452302327, "gender": "m", "verified": false, "verified_type": -1, "uid": "5161754670"}, {"original_text": "//@老师木: 转发微博", "username": "互联网信息检索与挖掘", "province": 11, "statuses_count": 2661, "friends_count": 88, "city": 8, "text": "", "user_description": "", "mid": "3929303542187690", "verified_reason": "", "followers_count": 145, "parent": "3929240833439698", "t": 1452302430, "gender": "m", "verified": false, "verified_type": -1, "uid": "1865769965"}, {"original_text": " //@爱可可-爱生活://@陈天奇怪: 容器是机器学习很不错的选择，包括xgboost，mxnet 都已经可以上docker，比起YARN来是更加干净，不过因为JVM stack一直存在似乎还是YARN用的比较多 //@老师木: 转发微博", "username": "jjppa", "province": 100, "statuses_count": 507, "friends_count": 294, "city": 1000, "text": " ", "user_description": "", "mid": "3929303794259489", "verified_reason": "", "followers_count": 37, "parent": "3929283258590145", "t": 1452302490, "gender": "m", "verified": false, "verified_type": -1, "uid": "2142001643"}, {"original_text": " //@星空下的巫师://@老师木:转发微博", "username": "忧危积心", "province": 13, "statuses_count": 2188, "friends_count": 149, "city": 1000, "text": " ", "user_description": "", "mid": "3929304775728698", "verified_reason": "", "followers_count": 96, "parent": "3929263004515401", "t": 1452302724, "gender": "m", "verified": false, "verified_type": -1, "uid": "2102161234"}, {"original_text": "用GPU+CoreOS+Docker+TensorFlow搭建高效灵活的深度学习研发平台", "username": "小鬼发哥", "province": 44, "statuses_count": 2750, "friends_count": 891, "city": 1000, "text": "用GPU+CoreOS+Docker+TensorFlow搭建高效灵活的深度学习研发平台", "user_description": "", "mid": "3929305388423394", "verified_reason": "", "followers_count": 44, "parent": "3929237763783263", "t": 1452302869, "gender": "m", "verified": false, "verified_type": -1, "uid": "2656116612"}, {"original_text": "//@陈天奇怪:容器是机器学习很不错的选择，包括xgboost，mxnet 都已经可以上docker，比起YARN来是更加干净，不过因为JVM stack一直存在似乎还是YARN用的比较多 //@老师木: 转发微博", "username": "wht_121", "province": 12, "statuses_count": 13774, "friends_count": 408, "city": 6, "text": "", "user_description": "资料收集狂", "mid": "3929306566759454", "verified_reason": "", "followers_count": 48, "parent": "3929282357065057", "t": 1452303151, "gender": "m", "verified": false, "verified_type": -1, "uid": "2362412930"}, {"original_text": "//@周永_52ML: //@爱可可-爱生活://@陈天奇怪: 容器是机器学习很不错的选择，包括xgboost，mxnet 都已经可以上docker，比起YARN来是更加干净，不过因为JVM stack一直存在似乎还是YARN用的比较多 //@老师木: 转发微博", "username": "Barty", "province": 11, "statuses_count": 1433, "friends_count": 1000, "city": 8, "text": "", "user_description": "计蒜客打杂，2013年ACM总决赛27名", "mid": "3929306625521971", "verified_reason": "", "followers_count": 4877, "parent": "3929297582208575", "t": 1452303164, "gender": "m", "verified": false, "verified_type": 220, "uid": "1619905711"}, {"original_text": "//@陈天奇怪:容器是机器学习很不错的选择，包括xgboost，mxnet 都已经可以上docker，比起YARN来是更加干净，不过因为JVM stack一直存在似乎还是YARN用的比较多 //@老师木: 转发微博", "username": "liu_cx", "province": 11, "statuses_count": 520, "friends_count": 181, "city": 8, "text": "", "user_description": "", "mid": "3929309288923212", "verified_reason": "", "followers_count": 104, "parent": "3929282357065057", "t": 1452303800, "gender": "m", "verified": false, "verified_type": -1, "uid": "2627199070"}, {"original_text": " //@爱可可-爱生活://@陈天奇怪: 容器是机器学习很不错的选择，包括xgboost，mxnet 都已经可以上docker，比起YARN来是更加干净，不过因为JVM stack一直存在似乎还是YARN用的比较多 //@老师木: 转发微博", "username": "我可真烦人", "province": 22, "statuses_count": 634, "friends_count": 222, "city": 1, "text": " ", "user_description": "因为彼此才最好", "mid": "3929309305713027", "verified_reason": "", "followers_count": 77, "parent": "3929283258590145", "t": 1452303804, "gender": "m", "verified": false, "verified_type": -1, "uid": "1978363853"}, {"original_text": " //@陈天奇怪:容器是机器学习很不错的选择，包括xgboost，mxnet 都已经可以上docker，比起YARN来是更加干净，不过因为JVM stack一直存在似乎还是YARN用的比较多 //@老师木: 转发微博", "username": "zarchary-10", "province": 35, "statuses_count": 1412, "friends_count": 93, "city": 2, "text": " ", "user_description": "MT", "mid": "3929309704473730", "verified_reason": "", "followers_count": 62, "parent": "3929282357065057", "t": 1452303899, "gender": "m", "verified": false, "verified_type": -1, "uid": "2621632753"}, {"original_text": "//@爱可可-爱生活://@陈天奇怪: 容器是机器学习很不错的选择，包括xgboost，mxnet 都已经可以上docker，比起YARN来是更加干净，不过因为JVM stack一直存在似乎还是YARN用的比较多 //@老师木: 转发微博", "username": "桃园树", "province": 45, "statuses_count": 648, "friends_count": 234, "city": 9, "text": "", "user_description": "", "mid": "3929309792130844", "verified_reason": "", "followers_count": 33, "parent": "3929283258590145", "t": 1452303920, "gender": "m", "verified": false, "verified_type": -1, "uid": "1364874703"}, {"original_text": "转发微博", "username": "xjump", "province": 33, "statuses_count": 921, "friends_count": 499, "city": 1, "text": "转发微博", "user_description": "关注安全技术、黑客、人工智能。", "mid": "3929310303962386", "verified_reason": "", "followers_count": 91, "parent": "3929237763783263", "t": 1452304042, "gender": "m", "verified": false, "verified_type": -1, "uid": "2845438603"}, {"original_text": "//@陈天奇怪:容器是机器学习很不错的选择，包括xgboost，mxnet 都已经可以上docker，比起YARN来是更加干净，不过因为JVM stack一直存在似乎还是YARN用的比较多 //@老师木: 转发微博", "username": "唐源Terry", "province": 400, "statuses_count": 9, "friends_count": 18, "city": 1, "text": "", "user_description": "想走不一样的路", "mid": "3929311839238737", "verified_reason": "", "followers_count": 11, "parent": "3929282357065057", "t": 1452304408, "gender": "m", "verified": false, "verified_type": -1, "uid": "5681818134"}, {"original_text": "//@李武军nju: //@陈天奇怪:容器是机器学习很不错的选择，包括xgboost，mxnet 都已经可以上docker，比起YARN来是更加干净，不过因为JVM stack一直存在似乎还是YARN用的比较多 //@老师木: 转发微博", "username": "zhang_jin_CSU", "province": 43, "statuses_count": 1090, "friends_count": 63, "city": 1, "text": "", "user_description": "计算机视觉", "mid": "3929312082715567", "verified_reason": "", "followers_count": 7, "parent": "3929301667332319", "t": 1452304465, "gender": "m", "verified": false, "verified_type": -1, "uid": "1651904343"}, {"original_text": " //@陈天奇怪:容器是机器学习很不错的选择，包括xgboost，mxnet 都已经可以上docker，比起YARN来是更加干净，不过因为JVM stack一直存在似乎还是YARN用的比较多 //@老师木: 转发微博", "username": "海里的大树", "province": 11, "statuses_count": 1840, "friends_count": 321, "city": 5, "text": " ", "user_description": "以大多数人努力程度之低、都还没有到达跟人拼天赋的程度", "mid": "3929314762435988", "verified_reason": "", "followers_count": 359, "parent": "3929282357065057", "t": 1452305105, "gender": "m", "verified": false, "verified_type": 220, "uid": "1679052585"}, {"original_text": "//@陈天奇怪:容器是机器学习很不错的选择，包括xgboost，mxnet 都已经可以上docker，比起YARN来是更加干净，不过因为JVM stack一直存在似乎还是YARN用的比较多 //@老师木: 转发微博", "username": "神剑傲州_月生", "province": 11, "statuses_count": 2046, "friends_count": 137, "city": 5, "text": "", "user_description": "北京握奇数据系统有限公司副研究员", "mid": "3929317282936854", "verified_reason": "", "followers_count": 85, "parent": "3929282357065057", "t": 1452305705, "gender": "m", "verified": false, "verified_type": -1, "uid": "2133676575"}, {"original_text": "转发微博", "username": "isoft的天空", "province": 100, "statuses_count": 2678, "friends_count": 29, "city": 1000, "text": "转发微博", "user_description": "", "mid": "3929321658303116", "verified_reason": "", "followers_count": 13, "parent": "3929237763783263", "t": 1452306749, "gender": "m", "verified": false, "verified_type": -1, "uid": "1495199125"}, {"original_text": "转发微博", "username": "随风淡然既韬哥", "province": 44, "statuses_count": 6329, "friends_count": 228, "city": 1, "text": "转发微博", "user_description": "一个有梦和理想的高度现实主义者，做一个有担当的人", "mid": "3929322114786927", "verified_reason": "", "followers_count": 252, "parent": "3929237763783263", "t": 1452306857, "gender": "m", "verified": false, "verified_type": -1, "uid": "2358942182"}, {"original_text": " //@李武军nju: //@陈天奇怪:容器是机器学习很不错的选择，包括xgboost，mxnet 都已经可以上docker，比起YARN来是更加干净，不过因为JVM stack一直存在似乎还是YARN用的比较多 //@老师木: 转发微博", "username": "caibinbupt", "province": 44, "statuses_count": 9299, "friends_count": 1751, "city": 3, "text": " ", "user_description": "Hadooper@Tencent", "mid": "3929322366922457", "verified_reason": "", "followers_count": 1740, "parent": "3929301667332319", "t": 1452306917, "gender": "m", "verified": false, "verified_type": -1, "uid": "1401903381"}, {"original_text": "@我的印象笔记 ", "username": "期待爱上不完美的自己", "province": 11, "statuses_count": 5420, "friends_count": 177, "city": 8, "text": "@我的印象笔记 ", "user_description": "", "mid": "3929323318634190", "verified_reason": "", "followers_count": 140, "parent": "3929237763783263", "t": 1452307145, "gender": "f", "verified": false, "verified_type": -1, "uid": "1091743464"}, {"original_text": "转发微博", "username": "xiaoQ_亮亮", "province": 11, "statuses_count": 65, "friends_count": 52, "city": 8, "text": "转发微博", "user_description": "", "mid": "3929327638624742", "verified_reason": "", "followers_count": 23, "parent": "3929237763783263", "t": 1452308175, "gender": "m", "verified": false, "verified_type": -1, "uid": "1854092157"}, {"original_text": "//@爱可可-爱生活://@陈天奇怪: 容器是机器学习很不错的选择，包括xgboost，mxnet 都已经可以上docker，比起YARN来是更加干净，不过因为JVM stack一直存在似乎还是YARN用的比较多 //@老师木: 转发微博", "username": "yneversky", "province": 51, "statuses_count": 2517, "friends_count": 184, "city": 1, "text": "", "user_description": "川大计算机学院 研究兴趣：时空数据挖掘 社会网络分析 http://yneversky.sinaapp.com", "mid": "3929327802618664", "verified_reason": "", "followers_count": 84, "parent": "3929283258590145", "t": 1452308214, "gender": "m", "verified": false, "verified_type": -1, "uid": "1889625690"}, {"original_text": " //@李武军nju: //@陈天奇怪:容器是机器学习很不错的选择，包括xgboost，mxnet 都已经可以上docker，比起YARN来是更加干净，不过因为JVM stack一直存在似乎还是YARN用的比较多 //@老师木: 转发微博", "username": "虾米微虾米", "province": 35, "statuses_count": 2581, "friends_count": 1467, "city": 1, "text": " ", "user_description": "", "mid": "3929328738168898", "verified_reason": "", "followers_count": 87, "parent": "3929301667332319", "t": 1452308437, "gender": "m", "verified": false, "verified_type": -1, "uid": "2468718581"}, {"original_text": "//@李武军nju: //@陈天奇怪:容器是机器学习很不错的选择，包括xgboost，mxnet 都已经可以上docker，比起YARN来是更加干净，不过因为JVM stack一直存在似乎还是YARN用的比较多 //@老师木: 转发微博", "username": "菩提下的手掌心", "province": 31, "statuses_count": 2058, "friends_count": 329, "city": 19, "text": "", "user_description": "努力成为初级码农", "mid": "3929330113647611", "verified_reason": "", "followers_count": 247, "parent": "3929301667332319", "t": 1452308764, "gender": "f", "verified": false, "verified_type": -1, "uid": "2285705190"}, {"original_text": "mark//@李武军nju: //@陈天奇怪:容器是机器学习很不错的选择，包括xgboost，mxnet 都已经可以上docker，比起YARN来是更加干净，不过因为JVM stack一直存在似乎还是YARN用的比较多 //@老师木: 转发微博", "username": "齐天求长胖", "province": 11, "statuses_count": 94, "friends_count": 465, "city": 8, "text": "mark", "user_description": "", "mid": "3929333724728915", "verified_reason": "", "followers_count": 56, "parent": "3929301667332319", "t": 1452309626, "gender": "m", "verified": false, "verified_type": -1, "uid": "2112679933"}, {"original_text": "//@李武军nju: //@陈天奇怪:容器是机器学习很不错的选择，包括xgboost，mxnet 都已经可以上docker，比起YARN来是更加干净，不过因为JVM stack一直存在似乎还是YARN用的比较多 //@老师木: 转发微博", "username": "樵夫上校", "province": 42, "statuses_count": 3160, "friends_count": 580, "city": 1, "text": "", "user_description": "关注模式识别，计算机视觉，机器学习，视觉跟踪，目标检测识别，以及八卦娱乐~~", "mid": "3929334585102996", "verified_reason": "", "followers_count": 596, "parent": "3929301667332319", "t": 1452309831, "gender": "m", "verified": false, "verified_type": 220, "uid": "2162393553"}, {"original_text": "Repost", "username": "流茫_MachineLearning", "province": 32, "statuses_count": 1906, "friends_count": 70, "city": 1, "text": "Repost", "user_description": "Nothing is impossible! football！", "mid": "3929334627090759", "verified_reason": "", "followers_count": 27, "parent": "3929237763783263", "t": 1452309841, "gender": "m", "verified": false, "verified_type": -1, "uid": "3290056601"}, {"original_text": "转发微博", "username": "门外翰-云上", "province": 31, "statuses_count": 1855, "friends_count": 697, "city": 4, "text": "转发微博", "user_description": "", "mid": "3929335025390226", "verified_reason": "", "followers_count": 391, "parent": "3929237763783263", "t": 1452309936, "gender": "m", "verified": false, "verified_type": -1, "uid": "1635091883"}, {"original_text": "转发微博", "username": "吴亮亮_RUC", "province": 11, "statuses_count": 1131, "friends_count": 453, "city": 1000, "text": "转发微博", "user_description": "自从那天，我便深深爱上你", "mid": "3929335763189805", "verified_reason": "     \nHTML5前端开发工程师\n  网页设计师", "followers_count": 2883, "parent": "3929237763783263", "t": 1452310111, "gender": "m", "verified": true, "verified_type": 0, "uid": "2494720710"}, {"original_text": "//@爱可可-爱生活://@陈天奇怪: 容器是机器学习很不错的选择，包括xgboost，mxnet 都已经可以上docker，比起YARN来是更加干净，不过因为JVM stack一直存在似乎还是YARN用的比较多 //@老师木: 转发微博", "username": "LittleRemy", "province": 61, "statuses_count": 397, "friends_count": 18, "city": 1, "text": "", "user_description": "Remy is a little rat from disney land.", "mid": "3929338523153082", "verified_reason": "", "followers_count": 2, "parent": "3929283258590145", "t": 1452310770, "gender": "m", "verified": false, "verified_type": -1, "uid": "5540804153"}, {"original_text": "转发微博", "username": "Aaron兰塞", "province": 31, "statuses_count": 1931, "friends_count": 221, "city": 12, "text": "转发微博", "user_description": "", "mid": "3929339898785060", "verified_reason": "", "followers_count": 44, "parent": "3929237763783263", "t": 1452311097, "gender": "m", "verified": false, "verified_type": -1, "uid": "1809118673"}, {"original_text": "转发微博", "username": "冷水北京", "province": 11, "statuses_count": 5765, "friends_count": 458, "city": 28, "text": "转发微博", "user_description": "I don’t know if we each have a destiny, or if we’re all just floating around accidental—like on a breeze", "mid": "3929340322353394", "verified_reason": "", "followers_count": 390, "parent": "3929237763783263", "t": 1452311199, "gender": "m", "verified": false, "verified_type": -1, "uid": "1550914792"}, {"original_text": "//@爱可可-爱生活://@陈天奇怪: 容器是机器学习很不错的选择，包括xgboost，mxnet 都已经可以上docker，比起YARN来是更加干净，不过因为JVM stack一直存在似乎还是YARN用的比较多 //@老师木: 转发微博", "username": "eelileiscut", "province": 44, "statuses_count": 258, "friends_count": 59, "city": 1, "text": "", "user_description": "", "mid": "3929340973011618", "verified_reason": "", "followers_count": 13, "parent": "3929283258590145", "t": 1452311354, "gender": "m", "verified": false, "verified_type": -1, "uid": "2801433867"}, {"original_text": "Repost", "username": "CauchyNash光", "province": 400, "statuses_count": 307, "friends_count": 389, "city": 1, "text": "Repost", "user_description": "Before changing the world, change yourself.", "mid": "3929342109525073", "verified_reason": "", "followers_count": 107, "parent": "3929237763783263", "t": 1452311625, "gender": "m", "verified": false, "verified_type": -1, "uid": "1968363207"}, {"original_text": "//@陈天奇怪:容器是机器学习很不错的选择，包括xgboost，mxnet 都已经可以上docker，比起YARN来是更加干净，不过因为JVM stack一直存在似乎还是YARN用的比较多 //@老师木: 转发微博", "username": "_ml_fans", "province": 51, "statuses_count": 3155, "friends_count": 544, "city": 6, "text": "", "user_description": "读paper而不coding则罔，只coding而不啃paper则殆", "mid": "3929345733250544", "verified_reason": "", "followers_count": 841, "parent": "3929282357065057", "t": 1452312489, "gender": "m", "verified": false, "verified_type": -1, "uid": "1717217073"}, {"original_text": "docker让各种依赖库版本的程序部署变得前所未有的快速方便//@_ml_fans: //@陈天奇怪:容器是机器学习很不错的选择，包括xgboost，mxnet 都已经可以上docker，比起YARN来是更加干净，不过因为JVM stack一直存在似乎还是YARN用的比较多 //@老师木: 转发微博", "username": "KissDev", "province": 11, "statuses_count": 1536, "friends_count": 721, "city": 8, "text": "docker让各种依赖库版本的程序部署变得前所未有的快速方便", "user_description": "全栈程序员，不求甚解的实战主义者，爱旅游，爱美食", "mid": "3929352888601220", "verified_reason": "", "followers_count": 5988, "parent": "3929345733250544", "t": 1452314195, "gender": "m", "verified": false, "verified_type": -1, "uid": "1699016425"}, {"original_text": " //@李武军nju: //@陈天奇怪:容器是机器学习很不错的选择，包括xgboost，mxnet 都已经可以上docker，比起YARN来是更加干净，不过因为JVM stack一直存在似乎还是YARN用的比较多 //@老师木: 转发微博", "username": "搞笑人士", "province": 81, "statuses_count": 3931, "friends_count": 564, "city": 2, "text": " ", "user_description": "", "mid": "3929354109604885", "verified_reason": "", "followers_count": 1298, "parent": "3929301667332319", "t": 1452314485, "gender": "m", "verified": false, "verified_type": -1, "uid": "1857260162"}, {"original_text": "//@KissDev:docker让各种依赖库版本的程序部署变得前所未有的快速方便//@_ml_fans: //@陈天奇怪:容器是机器学习很不错的选择，包括xgboost，mxnet 都已经可以上docker，比起YARN来是更加干净，不过因为JVM stack一直存在似乎还是YARN用的比较多 //@老师木: 转发微博", "username": "microsvcv", "province": 31, "statuses_count": 3372, "friends_count": 1711, "city": 15, "text": "", "user_description": "意识，顾大局，识大体，胸怀宽广", "mid": "3929357234225160", "verified_reason": "", "followers_count": 409, "parent": "3929352888601220", "t": 1452315231, "gender": "m", "verified": false, "verified_type": -1, "uid": "1661970550"}, {"original_text": " //@陈天奇怪:容器是机器学习很不错的选择，包括xgboost，mxnet 都已经可以上docker，比起YARN来是更加干净，不过因为JVM stack一直存在似乎还是YARN用的比较多 //@老师木: 转发微博", "username": "穿靴子的肖小恩", "province": 32, "statuses_count": 104, "friends_count": 23, "city": 6, "text": " ", "user_description": "", "mid": "3929362531625253", "verified_reason": "", "followers_count": 19, "parent": "3929282357065057", "t": 1452316494, "gender": "m", "verified": false, "verified_type": -1, "uid": "2887658290"}, {"original_text": "转发微博", "username": "蒸包子的蒸", "province": 11, "statuses_count": 2734, "friends_count": 61, "city": 1, "text": "转发微博", "user_description": "", "mid": "3929362762518959", "verified_reason": "", "followers_count": 23, "parent": "3929237763783263", "t": 1452316548, "gender": "m", "verified": false, "verified_type": -1, "uid": "1806143207"}, {"original_text": "//@老师木:转发微博", "username": "阳光阿哈", "province": 11, "statuses_count": 1311, "friends_count": 156, "city": 8, "text": "", "user_description": "", "mid": "3929366033213363", "verified_reason": "", "followers_count": 20, "parent": "3929240833439698", "t": 1452317329, "gender": "m", "verified": false, "verified_type": -1, "uid": "1758682271"}, {"original_text": "@我的印象笔记 ", "username": "WebberHou", "province": 100, "statuses_count": 380, "friends_count": 77, "city": 1000, "text": "@我的印象笔记 ", "user_description": "", "mid": "3929366352004452", "verified_reason": "", "followers_count": 5, "parent": "3929237763783263", "t": 1452317405, "gender": "m", "verified": false, "verified_type": -1, "uid": "3251487894"}, {"original_text": " //@搞笑人士: //@李武军nju: //@陈天奇怪:容器是机器学习很不错的选择，包括xgboost，mxnet 都已经可以上docker，比起YARN来是更加干净，不过因为JVM stack一直存在似乎还是YARN用的比较多 //@老师木: 转发微博", "username": "绝对零度yukoon", "province": 32, "statuses_count": 3842, "friends_count": 98, "city": 1, "text": " ", "user_description": "PhD,关注自然语言处理、机器翻译、深度学习", "mid": "3929373856312412", "verified_reason": "", "followers_count": 308, "parent": "3929354109604885", "t": 1452319194, "gender": "m", "verified": false, "verified_type": -1, "uid": "1738403510"}, {"original_text": "转发微博", "username": "大勺小忽悠", "province": 11, "statuses_count": 1254, "friends_count": 60, "city": 8, "text": "转发微博", "user_description": "", "mid": "3929376942759807", "verified_reason": "", "followers_count": 104, "parent": "3929237763783263", "t": 1452319930, "gender": "m", "verified": false, "verified_type": -1, "uid": "1106203500"}, {"original_text": "转发微博", "username": "樊永显", "province": 45, "statuses_count": 1898, "friends_count": 133, "city": 3, "text": "转发微博", "user_description": "", "mid": "3929377501159725", "verified_reason": "", "followers_count": 17, "parent": "3929237763783263", "t": 1452320063, "gender": "m", "verified": false, "verified_type": -1, "uid": "3850850547"}, {"original_text": "//@老师木:转发微博", "username": "潜龙在渊其势飞天", "province": 32, "statuses_count": 7391, "friends_count": 229, "city": 1, "text": "", "user_description": "", "mid": "3929387919640687", "verified_reason": "", "followers_count": 118, "parent": "3929240833439698", "t": 1452322547, "gender": "m", "verified": false, "verified_type": -1, "uid": "2301568994"}, {"original_text": "//@爱可可-爱生活://@陈天奇怪: 容器是机器学习很不错的选择，包括xgboost，mxnet 都已经可以上docker，比起YARN来是更加干净，不过因为JVM stack一直存在似乎还是YARN用的比较多 //@老师木: 转发微博", "username": "TopwalkSnail", "province": 11, "statuses_count": 320, "friends_count": 102, "city": 8, "text": "", "user_description": "", "mid": "3929391765152272", "verified_reason": "", "followers_count": 19, "parent": "3929283258590145", "t": 1452323463, "gender": "m", "verified": false, "verified_type": -1, "uid": "3202089305"}, {"original_text": "//@搞笑人士: //@李武军nju: //@陈天奇怪:容器是机器学习很不错的选择，包括xgboost，mxnet 都已经可以上docker，比起YARN来是更加干净，不过因为JVM stack一直存在似乎还是YARN用的比较多 //@老师木: 转发微博", "username": "LR机器学习计算机视觉", "province": 11, "statuses_count": 20667, "friends_count": 968, "city": 5, "text": "", "user_description": "北京工业大学软件学院讲师李蓉，专注计算机视觉和机器学习", "mid": "3929392210282195", "verified_reason": "", "followers_count": 6826, "parent": "3929354109604885", "t": 1452323570, "gender": "f", "verified": false, "verified_type": -1, "uid": "3209669611"}, {"original_text": "//@爱可可-爱生活: //@陈天奇怪: 容器是机器学习很不错的选择，包括xgboost，mxnet 都已经可以上docker，比起YARN来是更加干净，不过因为JVM stack一直存在似乎还是YARN用的比较多 //@老师木: 转发微博", "username": "hbyido", "province": 33, "statuses_count": 53945, "friends_count": 1400, "city": 1, "text": "", "user_description": "记录时代", "mid": "3929393665917980", "verified_reason": "", "followers_count": 3523, "parent": "3929283258590145", "t": 1452323917, "gender": "m", "verified": false, "verified_type": -1, "uid": "1646706835"}, {"original_text": "//@爱可可-爱生活: //@陈天奇怪: 容器是机器学习很不错的选择，包括xgboost，mxnet 都已经可以上docker，比起YARN来是更加干净，不过因为JVM stack一直存在似乎还是YARN用的比较多 //@老师木: 转发微博", "username": "hbyido", "province": 33, "statuses_count": 53945, "friends_count": 1400, "city": 1, "text": "", "user_description": "记录时代", "mid": "3929394856351999", "verified_reason": "", "followers_count": 3523, "parent": "3929283258590145", "t": 1452324201, "gender": "m", "verified": false, "verified_type": -1, "uid": "1646706835"}, {"original_text": " //@LR机器学习计算机视觉://@搞笑人士: //@李武军nju: //@陈天奇怪:容器是机器学习很不错的选择，包括xgboost，mxnet 都已经可以上docker，比起YARN来是更加干净，不过因为JVM stack一直存在似乎还是YARN用的比较多 //@老师木: 转发微博", "username": "ericshape", "province": 400, "statuses_count": 2415, "friends_count": 335, "city": 1, "text": " ", "user_description": "Hokie, Hokie, Hi~ @ Grenoble, France; @ San Francisco, CA; @ Blacksburg, VA https://www.facebook.com/ericshape", "mid": "3929398614493044", "verified_reason": "", "followers_count": 317, "parent": "3929392210282195", "t": 1452325096, "gender": "m", "verified": false, "verified_type": -1, "uid": "1411371242"}, {"original_text": " @我的印象笔记", "username": "李光夏", "province": 31, "statuses_count": 1301, "friends_count": 405, "city": 12, "text": " @我的印象笔记", "user_description": "", "mid": "3929399927734570", "verified_reason": "", "followers_count": 114, "parent": "3929237763783263", "t": 1452325410, "gender": "m", "verified": false, "verified_type": -1, "uid": "1559081552"}, {"original_text": "//@爱可可-爱生活://@陈天奇怪: 容器是机器学习很不错的选择，包括xgboost，mxnet 都已经可以上docker，比起YARN来是更加干净，不过因为JVM stack一直存在似乎还是YARN用的比较多 //@老师木: 转发微博", "username": "槟糖微博", "province": 44, "statuses_count": 1944, "friends_count": 243, "city": 3, "text": "", "user_description": "坚信你所做的，并坚持做下去。", "mid": "3929401449883588", "verified_reason": "", "followers_count": 263, "parent": "3929283258590145", "t": 1452325772, "gender": "m", "verified": false, "verified_type": -1, "uid": "2100610530"}, {"original_text": "转发微博", "username": "love-life蕊铊铊", "province": 11, "statuses_count": 357, "friends_count": 39, "city": 1, "text": "转发微博", "user_description": "疼爱你 是我们在一起的最大理由", "mid": "3929404587357774", "verified_reason": "", "followers_count": 20, "parent": "3929237763783263", "t": 1452326521, "gender": "f", "verified": false, "verified_type": -1, "uid": "5493197512"}, {"original_text": "//@李武军nju: //@陈天奇怪:容器是机器学习很不错的选择，包括xgboost，mxnet 都已经可以上docker，比起YARN来是更加干净，不过因为JVM stack一直存在似乎还是YARN用的比较多 //@老师木: 转发微博", "username": "李鸢gasover", "province": 50, "statuses_count": 31406, "friends_count": 1965, "city": 7, "text": "", "user_description": "心如工画师，能画诸世间。五蕴悉从生，无法而不造。", "mid": "3929409004319878", "verified_reason": "", "followers_count": 411, "parent": "3929301667332319", "t": 1452327574, "gender": "m", "verified": false, "verified_type": -1, "uid": "1742011211"}, {"original_text": "转发微博", "username": "小眼看新闻", "province": 400, "statuses_count": 21, "friends_count": 32, "city": 1000, "text": "转发微博", "user_description": "小号看新闻~~", "mid": "3929410858332526", "verified_reason": "", "followers_count": 3, "parent": "3929237763783263", "t": 1452328015, "gender": "m", "verified": false, "verified_type": -1, "uid": "5657370902"}, {"original_text": " //@老师木:转发微博", "username": "Noodles-Xu", "province": 31, "statuses_count": 29969, "friends_count": 286, "city": 15, "text": " ", "user_description": "成功才快乐", "mid": "3929411311218495", "verified_reason": "", "followers_count": 590, "parent": "3929240833439698", "t": 1452328123, "gender": "m", "verified": false, "verified_type": -1, "uid": "1908599781"}, {"original_text": "转发微博", "username": "Noodles-Xu", "province": 31, "statuses_count": 29969, "friends_count": 286, "city": 15, "text": "转发微博", "user_description": "成功才快乐", "mid": "3929411474938525", "verified_reason": "", "followers_count": 590, "parent": "3929237763783263", "t": 1452328163, "gender": "m", "verified": false, "verified_type": -1, "uid": "1908599781"}, {"original_text": "//@Noodles-Xu:转发微博", "username": "今朝少年", "province": 11, "statuses_count": 1270, "friends_count": 224, "city": 5, "text": "", "user_description": "", "mid": "3929412149841174", "verified_reason": "", "followers_count": 45, "parent": "3929411474938525", "t": 1452328323, "gender": "m", "verified": false, "verified_type": -1, "uid": "2356671900"}, {"original_text": "//@陈天奇怪:容器是机器学习很不错的选择，包括xgboost，mxnet 都已经可以上docker，比起YARN来是更加干净，不过因为JVM stack一直存在似乎还是YARN用的比较多 //@老师木: 转发微博", "username": "hbyido", "province": 33, "statuses_count": 53945, "friends_count": 1400, "city": 1, "text": "", "user_description": "记录时代", "mid": "3929412917143955", "verified_reason": "", "followers_count": 3523, "parent": "3929345733250544", "t": 1452328507, "gender": "m", "verified": false, "verified_type": -1, "uid": "1646706835"}, {"original_text": "转发微博", "username": "json_decode", "province": 33, "statuses_count": 2006, "friends_count": 101, "city": 5, "text": "转发微博", "user_description": "一句话介绍", "mid": "3929413034687176", "verified_reason": "", "followers_count": 88, "parent": "3929237763783263", "t": 1452328535, "gender": "m", "verified": false, "verified_type": -1, "uid": "1256359143"}, {"original_text": "转发微博", "username": "dinoworld", "province": 42, "statuses_count": 270, "friends_count": 122, "city": 1, "text": "转发微博", "user_description": "", "mid": "3929413219393456", "verified_reason": "", "followers_count": 11, "parent": "3929237763783263", "t": 1452328579, "gender": "m", "verified": false, "verified_type": -1, "uid": "2166478627"}, {"original_text": "//@hbyido://@陈天奇怪:容器是机器学习很不错的选择，包括xgboost，mxnet 都已经可以上docker，比起YARN来是更加干净，不过因为JVM stack一直存在似乎还是YARN用的比较多 //@老师木: 转发微博", "username": "ShenLanSDU", "province": 37, "statuses_count": 2656, "friends_count": 2295, "city": 1, "text": "", "user_description": "大数据,云网络,云计算,云机器人,云存储,分布式计算与系统,虚拟化与SDN,物联网,量子信息,ITS,智能家居,数据可视化,知识工程,智慧城市,智能视频识别。", "mid": "3929414720597520", "verified_reason": "", "followers_count": 194, "parent": "3929412917143955", "t": 1452328936, "gender": "m", "verified": false, "verified_type": -1, "uid": "3840084453"}, {"original_text": "//@爱可可-爱生活: //@陈天奇怪: 容器是机器学习很不错的选择，包括xgboost，mxnet 都已经可以上docker，比起YARN来是更加干净，不过因为JVM stack一直存在似乎还是YARN用的比较多 //@老师木: 转发微博", "username": "李鸢gasover", "province": 50, "statuses_count": 31406, "friends_count": 1965, "city": 7, "text": "", "user_description": "心如工画师，能画诸世间。五蕴悉从生，无法而不造。", "mid": "3929417594389165", "verified_reason": "", "followers_count": 411, "parent": "3929283258590145", "t": 1452329622, "gender": "m", "verified": false, "verified_type": -1, "uid": "1742011211"}, {"original_text": "//@老师木:转发微博", "username": "ycp107被抢注", "province": 32, "statuses_count": 1145, "friends_count": 171, "city": 1, "text": "", "user_description": "龙腾虎跃", "mid": "3929418869174345", "verified_reason": "", "followers_count": 82, "parent": "3929240833439698", "t": 1452329926, "gender": "m", "verified": false, "verified_type": -1, "uid": "2511504650"}, {"original_text": " //@LR机器学习计算机视觉://@搞笑人士: //@李武军nju: //@陈天奇怪:容器是机器学习很不错的选择，包括xgboost，mxnet 都已经可以上docker，比起YARN来是更加干净，不过因为JVM stack一直存在似乎还是YARN用的比较多 //@老师木: 转发微博", "username": "mofupaca", "province": 400, "statuses_count": 1233, "friends_count": 86, "city": 15, "text": " ", "user_description": "駅memo(首都圈master)、小田急60000型/京成skyliner/super azusa、machine learning研究中", "mid": "3929419959828274", "verified_reason": "", "followers_count": 150, "parent": "3929392210282195", "t": 1452330186, "gender": "m", "verified": false, "verified_type": -1, "uid": "2373576685"}, {"original_text": "//@爱可可-爱生活: //@陈天奇怪: 容器是机器学习很不错的选择，包括xgboost，mxnet 都已经可以上docker，比起YARN来是更加干净，不过因为JVM stack一直存在似乎还是YARN用的比较多 //@老师木: 转发微博", "username": "行者行殇", "province": 43, "statuses_count": 10890, "friends_count": 176, "city": 1, "text": "", "user_description": "科研狗", "mid": "3929426074716516", "verified_reason": "", "followers_count": 53, "parent": "3929283258590145", "t": 1452331644, "gender": "m", "verified": false, "verified_type": -1, "uid": "3735078562"}, {"original_text": "Repost", "username": "shwifa", "province": 400, "statuses_count": 987, "friends_count": 35, "city": 16, "text": "Repost", "user_description": "", "mid": "3929427215531790", "verified_reason": "", "followers_count": 26, "parent": "3929237763783263", "t": 1452331916, "gender": "m", "verified": false, "verified_type": -1, "uid": "3178678635"}, {"original_text": "转发微博", "username": "二进制ZYX", "province": 43, "statuses_count": 2575, "friends_count": 307, "city": 1, "text": "转发微博", "user_description": "", "mid": "3929430877235039", "verified_reason": "", "followers_count": 167, "parent": "3929237763783263", "t": 1452332788, "gender": "m", "verified": false, "verified_type": -1, "uid": "2300394567"}, {"original_text": "//@KissDev:docker让各种依赖库版本的程序部署变得前所未有的快速方便//@_ml_fans: //@陈天奇怪:容器是机器学习很不错的选择，包括xgboost，mxnet 都已经可以上docker，比起YARN来是更加干净，不过因为JVM stack一直存在似乎还是YARN用的比较多 //@老师木: 转发微博", "username": "砰砰的小屋", "province": 32, "statuses_count": 22378, "friends_count": 1788, "city": 2, "text": "", "user_description": "", "mid": "3929435592284467", "verified_reason": "", "followers_count": 511, "parent": "3929352888601220", "t": 1452333913, "gender": "f", "verified": false, "verified_type": -1, "uid": "2036923815"}, {"original_text": "//@爱可可-爱生活://@陈天奇怪: 容器是机器学习很不错的选择，包括xgboost，mxnet 都已经可以上docker，比起YARN来是更加干净，不过因为JVM stack一直存在似乎还是YARN用的比较多 //@老师木: 转发微博", "username": "海_大_星", "province": 11, "statuses_count": 5476, "friends_count": 173, "city": 8, "text": "", "user_description": "", "mid": "3929440692271911", "verified_reason": "", "followers_count": 6, "parent": "3929283258590145", "t": 1452335128, "gender": "m", "verified": false, "verified_type": -1, "uid": "2287952254"}, {"original_text": "转发微博", "username": "社会青年932", "province": 11, "statuses_count": 222, "friends_count": 72, "city": 1000, "text": "转发微博", "user_description": "", "mid": "3929445745994576", "verified_reason": "", "followers_count": 12, "parent": "3929237763783263", "t": 1452336333, "gender": "m", "verified": false, "verified_type": -1, "uid": "5685057567"}, {"original_text": " //@LR机器学习计算机视觉://@搞笑人士: //@李武军nju: //@陈天奇怪:容器是机器学习很不错的选择，包括xgboost，mxnet 都已经可以上docker，比起YARN来是更加干净，不过因为JVM stack一直存在似乎还是YARN用的比较多 //@老师木: 转发微博", "username": "luweiming", "province": 33, "statuses_count": 5253, "friends_count": 136, "city": 1, "text": " ", "user_description": "", "mid": "3929450447831722", "verified_reason": "", "followers_count": 64, "parent": "3929392210282195", "t": 1452337455, "gender": "m", "verified": false, "verified_type": -1, "uid": "1938575460"}, {"original_text": "//@绝对零度yukoon: //@搞笑人士: //@李武军nju: //@陈天奇怪:容器是机器学习很不错的选择，包括xgboost，mxnet 都已经可以上docker，比起YARN来是更加干净，不过因为JVM stack一直存在似乎还是YARN用的比较多 //@老师木: 转发微博", "username": "蔡振闹", "province": 33, "statuses_count": 733, "friends_count": 494, "city": 3, "text": "", "user_description": "大罗山脚下，一异客", "mid": "3929461575230629", "verified_reason": "", "followers_count": 90, "parent": "3929373856312412", "t": 1452340108, "gender": "m", "verified": false, "verified_type": -1, "uid": "2015936271"}, {"original_text": "Repost", "username": "小小哇嘎哩", "province": 51, "statuses_count": 72, "friends_count": 57, "city": 1, "text": "Repost", "user_description": "新的开始，新的梦想：）", "mid": "3929471000430608", "verified_reason": "", "followers_count": 74, "parent": "3929237763783263", "t": 1452342355, "gender": "m", "verified": false, "verified_type": -1, "uid": "1936479184"}, {"original_text": "→_→", "username": "Just--DeSk", "province": 43, "statuses_count": 1304, "friends_count": 288, "city": 1, "text": "→_→", "user_description": "早睡，多喝水，吃青菜", "mid": "3929474166920220", "verified_reason": "", "followers_count": 160, "parent": "3929237763783263", "t": 1452343110, "gender": "f", "verified": false, "verified_type": -1, "uid": "3126052997"}, {"original_text": "Repost", "username": "ZenoPeng", "province": 44, "statuses_count": 96, "friends_count": 72, "city": 1, "text": "Repost", "user_description": "", "mid": "3929481314342905", "verified_reason": "", "followers_count": 41, "parent": "3929237763783263", "t": 1452344814, "gender": "m", "verified": false, "verified_type": -1, "uid": "1798154350"}, {"original_text": "//@爱可可-爱生活://@陈天奇怪: 容器是机器学习很不错的选择，包括xgboost，mxnet 都已经可以上docker，比起YARN来是更加干净，不过因为JVM stack一直存在似乎还是YARN用的比较多 //@老师木: 转发微博", "username": "陆璎", "province": 400, "statuses_count": 4440, "friends_count": 47, "city": 1000, "text": "", "user_description": "陆璎", "mid": "3929481506527150", "verified_reason": "", "followers_count": 18, "parent": "3929283258590145", "t": 1452344859, "gender": "m", "verified": false, "verified_type": -1, "uid": "1847725977"}, {"original_text": "转发微博", "username": "奔跑中的CR", "province": 21, "statuses_count": 403, "friends_count": 103, "city": 2, "text": "转发微博", "user_description": "一双脚 能去丈量这个世界吗?", "mid": "3929486757848615", "verified_reason": "", "followers_count": 61, "parent": "3929237763783263", "t": 1452346112, "gender": "m", "verified": false, "verified_type": -1, "uid": "1731398621"}, {"original_text": "//@老师木:转发微博", "username": "eternal03_01", "province": 23, "statuses_count": 1254, "friends_count": 163, "city": 1, "text": "", "user_description": "", "mid": "3929490206437570", "verified_reason": "", "followers_count": 36, "parent": "3929240833439698", "t": 1452346934, "gender": "m", "verified": false, "verified_type": -1, "uid": "1299751934"}, {"original_text": "转发微博", "username": "无忌老爹", "province": 11, "statuses_count": 3977, "friends_count": 1289, "city": 1, "text": "转发微博", "user_description": "北京邮电大学 张闯，无忌他爹，教书匠一枚，偶尔行走江湖，寻求创新、跨界生存、读万卷书、行万里路，人到中年，依然在路上......", "mid": "3929493720361213", "verified_reason": "", "followers_count": 1685, "parent": "3929237763783263", "t": 1452347772, "gender": "m", "verified": false, "verified_type": 220, "uid": "1354105220"}, {"original_text": "//@蔡振闹: //@绝对零度yukoon: //@搞笑人士: //@李武军nju: //@陈天奇怪:容器是机器学习很不错的选择，包括xgboost，mxnet 都已经可以上docker，比起YARN来是更加干净，不过因为JVM stack一直存在似乎还是YARN用的比较多 //@老师木: 转发微博", "username": "LR机器学习计算机视觉", "province": 11, "statuses_count": 20667, "friends_count": 968, "city": 5, "text": "", "user_description": "北京工业大学软件学院讲师李蓉，专注计算机视觉和机器学习", "mid": "3929524460679567", "verified_reason": "", "followers_count": 6826, "parent": "3929461575230629", "t": 1452355101, "gender": "f", "verified": false, "verified_type": -1, "uid": "3209669611"}, {"original_text": "轉發微博", "username": "leboer1990", "province": 81, "statuses_count": 569, "friends_count": 124, "city": 1000, "text": "轉發微博", "user_description": "待我長髮及腰,少年娶我可好", "mid": "3929532195447685", "verified_reason": "", "followers_count": 38, "parent": "3929237763783263", "t": 1452356944, "gender": "m", "verified": false, "verified_type": -1, "uid": "2959464554"}, {"original_text": " //@李武军nju: //@陈天奇怪:容器是机器学习很不错的选择，包括xgboost，mxnet 都已经可以上docker，比起YARN来是更加干净，不过因为JVM stack一直存在似乎还是YARN用的比较多 //@老师木: 转发微博", "username": "全国人民被代表大会伪园长", "province": 11, "statuses_count": 3086, "friends_count": 485, "city": 1, "text": " ", "user_description": "请不要超过70个字", "mid": "3929534153793207", "verified_reason": "", "followers_count": 419, "parent": "3929301667332319", "t": 1452357412, "gender": "m", "verified": false, "verified_type": 220, "uid": "1912364041"}, {"original_text": "因吹斯挺 //@LR机器学习计算机视觉://@蔡振闹: //@绝对零度yukoon: //@搞笑人士: //@李武军nju: //@陈天奇怪:容器是机器学习很不错的选择，包括xgboost，mxnet 都已经可以上docker，比起YARN来是更加干净，不过因为JVM stack一直存在似乎还是YARN用的比较多 //@老师木: 转发微博", "username": "-掠太公", "province": 100, "statuses_count": 782, "friends_count": 691, "city": 1000, "text": "因吹斯挺 ", "user_description": "成熟内敛 勤劳勇敢 靠谱非常 肿么可能", "mid": "3929539279738300", "verified_reason": "", "followers_count": 153, "parent": "3929524460679567", "t": 1452358634, "gender": "m", "verified": false, "verified_type": -1, "uid": "1948200811"}, {"original_text": "//@LR机器学习计算机视觉：//@蔡振闹: //@绝对零度yukoon: //@搞笑人士: //@李武军nju: //@陈天奇怪:容器是机器学习很不错的选择，包括xgboost，mxnet 都已经可以上docker，比起YARN来是更加干净，不过因为JVM stack一直存在似乎还是YARN用的比较多 //@老师木: 转发微博", "username": "石博天的Research小马甲", "province": 11, "statuses_count": 667, "friends_count": 92, "city": 11, "text": "", "user_description": "此为马甲，大号请关注@石博天惊逗秋雨|白纸写代码,徒手焊电路.上能实验室,下可进课堂 | 代码洁癖的毕业党 | Deep Learning | Python |", "mid": "3929585953100898", "verified_reason": "", "followers_count": 43, "parent": "3929524460679567", "t": 1452369761, "gender": "m", "verified": false, "verified_type": -1, "uid": "5575626244"}, {"original_text": "//@LR机器学习计算机视觉://@蔡振闹: //@绝对零度yukoon: //@搞笑人士: //@李武军nju: //@陈天奇怪:容器是机器学习很不错的选择，包括xgboost，mxnet 都已经可以上docker，比起YARN来是更加干净，不过因为JVM stack一直存在似乎还是YARN用的比较多 //@老师木: 转发微博", "username": "LiPengSang", "province": 11, "statuses_count": 1875, "friends_count": 724, "city": 5, "text": "", "user_description": "Linux kernel, HPC, HSA, GPU Parallel computing", "mid": "3929650432577156", "verified_reason": "", "followers_count": 601, "parent": "3929524460679567", "t": 1452385135, "gender": "m", "verified": false, "verified_type": 220, "uid": "2160353033"}, {"original_text": "[围观]", "username": "天涯过客葱", "province": 11, "statuses_count": 9775, "friends_count": 1105, "city": 8, "text": "[围观]", "user_description": "时时可死 步步求生", "mid": "3929660561386264", "verified_reason": "", "followers_count": 1877, "parent": "3929237763783263", "t": 1452387549, "gender": "m", "verified": false, "verified_type": 220, "uid": "1866304395"}, {"original_text": "//@LR机器学习计算机视觉://@蔡振闹: //@绝对零度yukoon: //@搞笑人士: //@李武军nju: //@陈天奇怪:容器是机器学习很不错的选择，包括xgboost，mxnet 都已经可以上docker，比起YARN来是更加干净，不过因为JVM stack一直存在似乎还是YARN用的比较多 //@老师木: 转发微博", "username": "stone-mad", "province": 43, "statuses_count": 996, "friends_count": 233, "city": 3, "text": "", "user_description": "", "mid": "3929669508599646", "verified_reason": "", "followers_count": 27, "parent": "3929524460679567", "t": 1452389683, "gender": "m", "verified": false, "verified_type": -1, "uid": "3902260642"}, {"original_text": "转发微博", "username": "smashpumpkin", "province": 33, "statuses_count": 2416, "friends_count": 79, "city": 1, "text": "转发微博", "user_description": "", "mid": "3929680207727520", "verified_reason": "", "followers_count": 21, "parent": "3929237763783263", "t": 1452392234, "gender": "m", "verified": false, "verified_type": -1, "uid": "1683323141"}, {"original_text": "Repost", "username": "飞雪斯维因DXY", "province": 43, "statuses_count": 548, "friends_count": 189, "city": 1, "text": "Repost", "user_description": "心有多大 梦就有多大", "mid": "3929695655061449", "verified_reason": "", "followers_count": 164, "parent": "3929237763783263", "t": 1452395917, "gender": "f", "verified": false, "verified_type": -1, "uid": "1298682205"}, {"original_text": " //@LR机器学习计算机视觉://@蔡振闹: //@绝对零度yukoon: //@搞笑人士: //@李武军nju: //@陈天奇怪:容器是机器学习很不错的选择，包括xgboost，mxnet 都已经可以上docker，比起YARN来是更加干净，不过因为JVM stack一直存在似乎还是YARN用的比较多 //@老师木: 转发微博", "username": "休语栓", "province": 12, "statuses_count": 965, "friends_count": 304, "city": 4, "text": " ", "user_description": "", "mid": "3929697739768848", "verified_reason": "", "followers_count": 38, "parent": "3929524460679567", "t": 1452396414, "gender": "m", "verified": false, "verified_type": -1, "uid": "3612695711"}, {"original_text": "//@星空下的巫师: //@老师木:转发微博", "username": "hbyido", "province": 33, "statuses_count": 53945, "friends_count": 1400, "city": 1, "text": "", "user_description": "记录时代", "mid": "3929714417138000", "verified_reason": "", "followers_count": 3523, "parent": "3929263004515401", "t": 1452400390, "gender": "m", "verified": false, "verified_type": -1, "uid": "1646706835"}, {"original_text": " //@爱可可-爱生活://@陈天奇怪: 容器是机器学习很不错的选择，包括xgboost，mxnet 都已经可以上docker，比起YARN来是更加干净，不过因为JVM stack一直存在似乎还是YARN用的比较多 //@老师木: 转发微博", "username": "爱生活爱阿慌", "province": 46, "statuses_count": 2023, "friends_count": 334, "city": 1, "text": " ", "user_description": "cv-er也玩nlp, 客串search engine算法工程师。。。", "mid": "3929719361578677", "verified_reason": "", "followers_count": 235, "parent": "3929283258590145", "t": 1452401569, "gender": "m", "verified": false, "verified_type": 220, "uid": "1616292410"}, {"original_text": "//@老师木: 转发微博", "username": "wjzhang_ecnu", "province": 31, "statuses_count": 154, "friends_count": 102, "city": 7, "text": "", "user_description": "自信、开朗、90后...", "mid": "3929756116940981", "verified_reason": "", "followers_count": 42, "parent": "3929240833439698", "t": 1452410332, "gender": "m", "verified": false, "verified_type": -1, "uid": "2515151574"}, {"original_text": "//@老师木:转发微博", "username": "青粟子", "province": 32, "statuses_count": 1350, "friends_count": 92, "city": 8, "text": "", "user_description": "", "mid": "3929766854085666", "verified_reason": "", "followers_count": 40, "parent": "3929240833439698", "t": 1452412892, "gender": "m", "verified": false, "verified_type": -1, "uid": "3354047144"}, {"original_text": "@我的印象笔记 ", "username": "谢边边", "province": 51, "statuses_count": 2130, "friends_count": 998, "city": 1, "text": "@我的印象笔记 ", "user_description": "热爱：智能终端，PS3,跑步，毛笔字练习，钓鱼，读写code，研究软件架构，烙铁和命令行", "mid": "3929839813723681", "verified_reason": "", "followers_count": 414, "parent": "3929237763783263", "t": 1452430287, "gender": "m", "verified": false, "verified_type": 220, "uid": "1427847627"}, {"original_text": "转发微博", "username": "佛罗伦蒂诺_A_阿里萨", "province": 32, "statuses_count": 801, "friends_count": 179, "city": 5, "text": "转发微博", "user_description": "苔花如米小，也学牡丹开~~coding调bug。。", "mid": "3929847586028901", "verified_reason": "", "followers_count": 63, "parent": "3929237763783263", "t": 1452432140, "gender": "m", "verified": false, "verified_type": -1, "uid": "3109299677"}, {"original_text": "//@李武军nju: //@陈天奇怪:容器是机器学习很不错的选择，包括xgboost，mxnet 都已经可以上docker，比起YARN来是更加干净，不过因为JVM stack一直存在似乎还是YARN用的比较多 //@老师木: 转发微博", "username": "师傅的方式", "province": 36, "statuses_count": 4178, "friends_count": 115, "city": 10, "text": "", "user_description": "", "mid": "3929855248641393", "verified_reason": "", "followers_count": 12, "parent": "3929301667332319", "t": 1452433967, "gender": "m", "verified": false, "verified_type": -1, "uid": "1736727390"}, {"original_text": " //@陈天奇怪:容器是机器学习很不错的选择，包括xgboost，mxnet 都已经可以上docker，比起YARN来是更加干净，不过因为JVM stack一直存在似乎还是YARN用的比较多 //@老师木: 转发微博", "username": "大山数据科技", "province": 37, "statuses_count": 690, "friends_count": 90, "city": 6, "text": " ", "user_description": "为您插上数据智慧的翅膀！", "mid": "3929868254973842", "verified_reason": "烟台大山数据科技有限公司官方微博", "followers_count": 143, "parent": "3929282357065057", "t": 1452437067, "gender": "m", "verified": true, "verified_type": 2, "uid": "1131247877"}, {"original_text": "//@陈天奇怪: 容器是机器学习很不错的选择，包括xgboost，mxnet 都已经可以上docker，比起YARN来是更加干净，不过因为JVM stack一直存在似乎还是YARN用的比较多 //@老师木: 转发微博", "username": "迪拉克之塔", "province": 32, "statuses_count": 752, "friends_count": 476, "city": 1, "text": "", "user_description": "", "mid": "3930866508205822", "verified_reason": "", "followers_count": 174, "parent": "3929282357065057", "t": 1452675070, "gender": "m", "verified": false, "verified_type": -1, "uid": "1800301880"}, {"original_text": "为什么要用docker 还不知道 得多看看了 好流行现在@我的印象笔记  //@陈天奇怪:容器是机器学习很不错的选择，包括xgboost，mxnet 都已经可以上docker，比起YARN来是更加干净，不过因为JVM stack一直存在似乎还是YARN用的比较多 //@老师木: 转发微博", "username": "SiNZeRo", "province": 81, "statuses_count": 220, "friends_count": 934, "city": 15, "text": "为什么要用docker 还不知道 得多看看了 好流行现在@我的印象笔记  ", "user_description": "行拂乱其所为，所以动心忍性，曾益其所不能", "mid": "3931097085735090", "verified_reason": "", "followers_count": 656, "parent": "3929282357065057", "t": 1452730044, "gender": "m", "verified": false, "verified_type": -1, "uid": "1651821482"}, {"original_text": "转发微博", "username": "aoyingchen", "province": 42, "statuses_count": 1539, "friends_count": 590, "city": 1, "text": "转发微博", "user_description": "", "mid": "3932395331676351", "verified_reason": "", "followers_count": 18, "parent": "3929237763783263", "t": 1453039570, "gender": "m", "verified": false, "verified_type": -1, "uid": "3284800197"}, {"original_text": "转发微博", "username": "喝茶看电影", "province": 11, "statuses_count": 4574, "friends_count": 1278, "city": 1, "text": "转发微博", "user_description": "苦逼~~", "mid": "3933291176463764", "verified_reason": "", "followers_count": 1958, "parent": "3929237763783263", "t": 1453253155, "gender": "m", "verified": false, "verified_type": 220, "uid": "1407492652"}, {"original_text": "学习！//@喝茶看电影:转发微博", "username": "LeoLiuYan", "province": 31, "statuses_count": 903, "friends_count": 314, "city": 4, "text": "学习！", "user_description": "码农", "mid": "3933291843125674", "verified_reason": "", "followers_count": 46, "parent": "3933291176463764", "t": 1453253314, "gender": "m", "verified": false, "verified_type": -1, "uid": "3737714120"}, {"original_text": "//@老师木: 转发微博", "username": "YONGMING39", "province": 11, "statuses_count": 7565, "friends_count": 483, "city": 8, "text": "", "user_description": "要讲究不要将就", "mid": "3933516553065422", "verified_reason": "", "followers_count": 161, "parent": "3929240833439698", "t": 1453306889, "gender": "m", "verified": false, "verified_type": -1, "uid": "1768500331"}, {"original_text": "//@老师木:转发微博", "username": "ascendancyst", "province": 31, "statuses_count": 1233, "friends_count": 505, "city": 1, "text": "", "user_description": "la course aux étoiles, ça n'est pas pour moi. a dead man still walking in the reality distortion field.沉舟侧畔万木春，只心等待早超生。", "mid": "3934772851838789", "verified_reason": "", "followers_count": 72, "parent": "3929240833439698", "t": 1453606414, "gender": "m", "verified": false, "verified_type": -1, "uid": "2163580092"}, {"original_text": "转发微博", "username": "Oh_ma_Ya", "province": 400, "statuses_count": 455, "friends_count": 1630, "city": 1, "text": "转发微博", "user_description": "goat rodeo~~", "mid": "3940656467146764", "verified_reason": "", "followers_count": 128, "parent": "3929237763783263", "t": 1455009178, "gender": "m", "verified": false, "verified_type": -1, "uid": "1892347244"}, {"original_text": "转发微博", "username": "Felix大数据工程师", "province": 50, "statuses_count": 95, "friends_count": 308, "city": 8, "text": "转发微博", "user_description": "Hadoop开发、Spark开发、scala开发、Java开发、WinForm开发！", "mid": "3944610097045250", "verified_reason": "", "followers_count": 48, "parent": "3929237763783263", "t": 1455951797, "gender": "m", "verified": false, "verified_type": -1, "uid": "2168380925"}]