{"original_text": "【开源(Java):(Stanford NLP Group)最大熵分类器Stanford Classifer】\" a Java implementation of a maximum entropy classifier.\" http://t.cn/zYeOcYH 最新提供了Nodejs wrapper GitHub:http://t.cn/RUJ7I15", "evtlist": [498], "uid": "1402400261", "dep": 0, "text": "【开源(Java):(Stanford NLP Group)最大熵分类器Stanford Classifer】\" a Java implementation of a maximum entropy classifier.\" http://t.cn/zYeOcYH 最新提供了Nodejs wrapper GitHub:http://t.cn/RUJ7I15", "pid": "", "tr": 19, "mid": "3905012960493992", "times": 1, "childnum": 15, "t": 1446511104, "totalChildren": 19, "dr": 15, "children": [{"evtlist": [498], "uid": "3209669611", "dep": 0, "text": "转发微博", "pid": "3905012960493992", "tr": 1, "mid": "3905013137037428", "times": 1, "childnum": 1, "t": 1446511146, "totalChildren": 1, "dr": 1, "children": [{"evtlist": [498], "uid": "1908599781", "dep": 0, "text": " ", "pid": "3905013137037428", "tr": 0, "mid": "3905015922540544", "times": 1, "childnum": 0, "t": 1446511810, "totalChildren": 0, "dr": 0, "children": [], "name": "Noodles-Xu"}], "name": "LR机器学习计算机视觉"}, {"evtlist": [498], "uid": "1953075583", "dep": 0, "text": "转发微博", "pid": "3905012960493992", "tr": 0, "mid": "3905013367588872", "times": 1, "childnum": 0, "t": 1446511201, "totalChildren": 0, "dr": 0, "children": [], "name": "zhou_phd"}, {"evtlist": [498], "uid": "5667833209", "dep": 0, "text": "@我的映像笔记", "pid": "3905012960493992", "tr": 0, "mid": "3905017817410110", "times": 1, "childnum": 0, "t": 1446512262, "totalChildren": 0, "dr": 0, "children": [], "name": "一匹石头"}, {"evtlist": [498], "uid": "2362412930", "dep": 0, "text": "转发微博", "pid": "3905012960493992", "tr": 0, "mid": "3905028915923388", "times": 1, "childnum": 0, "t": 1446514908, "totalChildren": 0, "dr": 0, "children": [], "name": "wht_121"}, {"evtlist": [498], "uid": "3409153910", "dep": 0, "text": "转发微博", "pid": "3905012960493992", "tr": 0, "mid": "3905029142307331", "times": 1, "childnum": 0, "t": 1446514962, "totalChildren": 0, "dr": 0, "children": [], "name": "我不是咸鱼_Yuer"}, {"evtlist": [498], "uid": "2244354762", "dep": 0, "text": "转发微博", "pid": "3905012960493992", "tr": 0, "mid": "3905039955915034", "times": 1, "childnum": 0, "t": 1446517539, "totalChildren": 0, "dr": 0, "children": [], "name": "快乐寒暑假"}, {"evtlist": [498], "uid": "1835753761", "dep": 0, "text": "转发微博", "pid": "3905012960493992", "tr": 0, "mid": "3905041192643140", "times": 1, "childnum": 0, "t": 1446517834, "totalChildren": 0, "dr": 0, "children": [], "name": "huangchao的地盘"}, {"evtlist": [498], "uid": "1660464144", "dep": 0, "text": "转发微博", "pid": "3905012960493992", "tr": 0, "mid": "3905041427429864", "times": 1, "childnum": 0, "t": 1446517891, "totalChildren": 0, "dr": 0, "children": [], "name": "AllenIQY"}, {"evtlist": [498], "uid": "1815237617", "dep": 0, "text": "转发微博", "pid": "3905012960493992", "tr": 0, "mid": "3905065884245624", "times": 1, "childnum": 0, "t": 1446523722, "totalChildren": 0, "dr": 0, "children": [], "name": "喵星的汪"}, {"evtlist": [498], "uid": "1646706835", "dep": 0, "text": "转发微博", "pid": "3905012960493992", "tr": 3, "mid": "3905198064258909", "times": 1, "childnum": 3, "t": 1446555236, "totalChildren": 3, "dr": 3, "children": [{"evtlist": [498], "uid": "1707438033", "dep": 0, "text": "不能更赞了 ", "pid": "3905198064258909", "tr": 0, "mid": "3905203969284776", "times": 1, "childnum": 0, "t": 1446556643, "totalChildren": 0, "dr": 0, "children": [], "name": "周永_52ML"}, {"evtlist": [498], "uid": "5628022533", "dep": 0, "text": "", "pid": "3905198064258909", "tr": 0, "mid": "3905207240661274", "times": 1, "childnum": 0, "t": 1446557423, "totalChildren": 0, "dr": 0, "children": [], "name": "Aaroncbk"}, {"evtlist": [498], "uid": "1712745640", "dep": 0, "text": "@有道云笔记收藏 @我的印象笔记 ", "pid": "3905198064258909", "tr": 0, "mid": "3905364431056437", "times": 1, "childnum": 0, "t": 1446594900, "totalChildren": 0, "dr": 0, "children": [], "name": "进击的奉山"}], "name": "hbyido"}, {"evtlist": [498], "uid": "1659965751", "dep": 0, "text": "转发微博", "pid": "3905012960493992", "tr": 0, "mid": "3905201008757028", "times": 1, "childnum": 0, "t": 1446555938, "totalChildren": 0, "dr": 0, "children": [], "name": "加菲磕螺丝"}, {"evtlist": [498], "uid": "1791635983", "dep": 0, "text": "Repost", "pid": "3905012960493992", "tr": 0, "mid": "3905261623953982", "times": 1, "childnum": 0, "t": 1446570390, "totalChildren": 0, "dr": 0, "children": [], "name": "Jeven-Z"}, {"evtlist": [498], "uid": "2656116612", "dep": 0, "text": "开源(Java):(Stanford NLP Group)最大熵分类器Stanford Classifer", "pid": "3905012960493992", "tr": 0, "mid": "3905376594093251", "times": 1, "childnum": 0, "t": 1446597801, "totalChildren": 0, "dr": 0, "children": [], "name": "小鬼发哥"}, {"evtlist": [498], "uid": "1812766894", "dep": 0, "text": "转发微博", "pid": "3905012960493992", "tr": 0, "mid": "3905379144899535", "times": 1, "childnum": 0, "t": 1446598409, "totalChildren": 0, "dr": 0, "children": [], "name": "zhoujialincc"}, {"evtlist": [498], "uid": "1806143207", "dep": 0, "text": "转发微博", "pid": "3905012960493992", "tr": 0, "mid": "3905586359607930", "times": 1, "childnum": 0, "t": 1446647813, "totalChildren": 0, "dr": 0, "children": [], "name": "蒸包子的蒸"}], "name": "爱可可-爱生活"}