[{"original_text": "有人不惜采用最新最复杂的技术手段，把“胡同串子”司马南影响力降到最低。发张写字练习纸，也要被审过来审过去，甚至几天不放行。至于掉粉、丢粉、强行切断粉丝与我的联系，更是家常便饭。相信是有关方面高度重视我，在意志力方面刻意载培打磨我，我能经受得住这种考验吗？", "username": "司马南", "province": 11, "statuses_count": 27504, "friends_count": 2028, "city": 1000, "text": "有人不惜采用最新最复杂的技术手段，把“胡同串子”司马南影响力降到最低。发张写字练习纸，也要被审过来审过去，甚至几天不放行。至于掉粉、丢粉、强行切断粉丝与我的联系，更是家常便饭。相信是有关方面高度重视我，在意志力方面刻意载培打磨我，我能经受得住这种考验吗？", "user_description": "一介不入流之文人耳。喜附庸风雅，好舞文弄墨，敢班门弄斧，常标新立异。根性妄为，孤行一意，小民忧国，老瓜绿漆，学无所长，乐有所趣。", "mid": "3845367072792129", "verified_reason": "主持人，学者", "followers_count": 952360, "parent": "", "t": 1432290416, "gender": "m", "verified": true, "verified_type": 0, "uid": "1263406744"}, {"original_text": "呸，臭不要脸 。", "username": "慢半拍1981", "province": 62, "statuses_count": 1952, "friends_count": 479, "city": 1000, "text": "呸，臭不要脸 。", "user_description": "一个闲的蛋疼的闲人。", "mid": "3845367408126128", "verified_reason": "", "followers_count": 227, "parent": "3845367072792129", "t": 1432290496, "gender": "m", "verified": false, "verified_type": -1, "uid": "1193159890"}, {"original_text": "想到了.司马同志哥.你以为呢?", "username": "永乐大典丶", "province": 11, "statuses_count": 17416, "friends_count": 432, "city": 1, "text": "想到了.司马同志哥.你以为呢?", "user_description": "兴趣广泛，久经考验，物我两忘，心如水淡。人来人往皆为利,花开花落两由君。", "mid": "3845367688965305", "verified_reason": "", "followers_count": 333, "parent": "3845367072792129", "t": 1432290563, "gender": "m", "verified": false, "verified_type": -1, "uid": "5212475421"}, {"original_text": "草泥马的，能看见吗？", "username": "小踏板龟", "province": 100, "statuses_count": 1238, "friends_count": 1657, "city": 1000, "text": "草泥马的，能看见吗？", "user_description": "", "mid": "3845367911222661", "verified_reason": "", "followers_count": 134, "parent": "3845367072792129", "t": 1432290616, "gender": "m", "verified": false, "verified_type": -1, "uid": "1360860707"}, {"original_text": "看你以后再敢得罪我们和尚！", "username": "孔庆东", "province": 11, "statuses_count": 60805, "friends_count": 568, "city": 8, "text": "看你以后再敢得罪我们和尚！", "user_description": "联系讲座、会议、约稿、访谈、剪彩、顾问、嘉宾、策划、取名、占卜等严肃事项者，勿与本人联系，敬请发函至zhugebiyao@sina.com与魏先生联系。", "mid": "3845368045582125", "verified_reason": "北京大学中文系教授孔庆东", "followers_count": 2851364, "parent": "3845367072792129", "t": 1432290648, "gender": "m", "verified": true, "verified_type": 0, "uid": "1198367585"}, {"original_text": "转发微博", "username": "洎水西流", "province": 36, "statuses_count": 5255, "friends_count": 509, "city": 2, "text": "转发微博", "user_description": "为有牺牲多壮志，敢叫日月换新天！", "mid": "3845368183865906", "verified_reason": "", "followers_count": 229, "parent": "3845367072792129", "t": 1432290681, "gender": "m", "verified": false, "verified_type": -1, "uid": "2645073092"}, {"original_text": "这里也是他们的战略合作伙伴？[疑问]", "username": "二月鸟闲", "province": 22, "statuses_count": 9800, "friends_count": 102, "city": 1, "text": "这里也是他们的战略合作伙伴？[疑问]", "user_description": "", "mid": "3845368205047556", "verified_reason": "", "followers_count": 157, "parent": "3845367072792129", "t": 1432290686, "gender": "m", "verified": false, "verified_type": -1, "uid": "1660362727"}, {"original_text": "[哈哈] //@孔庆东:看你以后再敢得罪我们和尚！", "username": "羲和旸谷太阳马车999", "province": 11, "statuses_count": 43243, "friends_count": 2000, "city": 1, "text": "[哈哈] ", "user_description": "羲和羲和，汝奚汩没于荒淫之波。。。力哲学发现力行者！", "mid": "3845368217449084", "verified_reason": "", "followers_count": 3670, "parent": "3845368045582125", "t": 1432290689, "gender": "m", "verified": false, "verified_type": -1, "uid": "3838052602"}, {"original_text": "写果敢历史的我可没有什么影响力还不是天天被骂，不过我也很开心，有的人离不开我，通过骂我来提醒我也非常重要！", "username": "异域原乡人", "province": 400, "statuses_count": 4963, "friends_count": 618, "city": 1, "text": "写果敢历史的我可没有什么影响力还不是天天被骂，不过我也很开心，有的人离不开我，通过骂我来提醒我也非常重要！", "user_description": "缅甸果敢地区第一手新鲜资讯权威发布、最及时的新闻报道、事件解读", "mid": "3845368289007220", "verified_reason": "缅甸掸邦果敢自治区领导委员会办公室外宣职员", "followers_count": 1770, "parent": "3845367072792129", "t": 1432290706, "gender": "m", "verified": true, "verified_type": 0, "uid": "5520630030"}, {"original_text": "[哈哈][哈哈]//@孔庆东:看你以后再敢得罪我们和尚！", "username": "咖啡加盐114", "province": 50, "statuses_count": 9583, "friends_count": 121, "city": 1000, "text": "[哈哈][哈哈]", "user_description": "微博如擂台，理智对理智，偏激对偏激，你若畜生，我便屠夫！", "mid": "3845368301602252", "verified_reason": "", "followers_count": 113, "parent": "3845368045582125", "t": 1432290709, "gender": "m", "verified": false, "verified_type": -1, "uid": "1314121063"}, {"original_text": "//@孔庆东: 看你以后再敢得罪我们和尚！", "username": "东风来雨", "province": 37, "statuses_count": 11053, "friends_count": 487, "city": 1000, "text": "", "user_description": "诗人兴会更无前。", "mid": "3845368519644610", "verified_reason": "", "followers_count": 1189, "parent": "3845368045582125", "t": 1432290761, "gender": "m", "verified": false, "verified_type": -1, "uid": "3874017039"}, {"original_text": "没注意你原有多少粉，我只看到@千钧客 原有11万多粉，现在掉到9千多粉，不知浪浪搞什么鬼？！", "username": "情系丹江", "province": 41, "statuses_count": 32060, "friends_count": 553, "city": 1, "text": "没注意你原有多少粉，我只看到@千钧客 原有11万多粉，现在掉到9千多粉，不知浪浪搞什么鬼？！", "user_description": "领导我们事业的核心力量是中国共产党，指导我们思想的理论基础是马列主义毛泽东思想！", "mid": "3845368519643444", "verified_reason": "河南南阳宛淅凌岗凌氏宗族理事会 秘书长、谱书主编凌建学", "followers_count": 3352, "parent": "3845367072792129", "t": 1432290761, "gender": "m", "verified": true, "verified_type": 0, "uid": "3118531003"}, {"original_text": "主要怕错别字现眼[偷笑]//@孔庆东:看你以后再敢得罪我们和尚！", "username": "大地色浪", "province": 11, "statuses_count": 6574, "friends_count": 693, "city": 1, "text": "主要怕错别字现眼[偷笑]", "user_description": "", "mid": "3845368783678032", "verified_reason": "", "followers_count": 211, "parent": "3845368045582125", "t": 1432290822, "gender": "m", "verified": false, "verified_type": -1, "uid": "2172484675"}, {"original_text": "[吃惊]", "username": "frank258", "province": 21, "statuses_count": 6512, "friends_count": 786, "city": 2, "text": "[吃惊]", "user_description": "", "mid": "3845368851050313", "verified_reason": "", "followers_count": 171, "parent": "3845367072792129", "t": 1432290839, "gender": "m", "verified": false, "verified_type": -1, "uid": "1433189720"}, {"original_text": "转发微博", "username": "职业写手穿马甲", "province": 31, "statuses_count": 3481, "friends_count": 302, "city": 1000, "text": "转发微博", "user_description": "中医不过是有意无意的骗子-鲁迅", "mid": "3845368901220178", "verified_reason": "", "followers_count": 562, "parent": "3845367072792129", "t": 1432290851, "gender": "m", "verified": false, "verified_type": 220, "uid": "1887938261"}, {"original_text": "司马习字的古诗里，有敏感词汇。[嘻嘻][嘻嘻][嘻嘻] //@孔庆东:看你以后再敢得罪我们和尚！", "username": "晁之立", "province": 21, "statuses_count": 2313, "friends_count": 95, "city": 7, "text": "司马习字的古诗里，有敏感词汇。[嘻嘻][嘻嘻][嘻嘻] ", "user_description": "", "mid": "3845369156465325", "verified_reason": "", "followers_count": 53, "parent": "3845368045582125", "t": 1432290913, "gender": "m", "verified": false, "verified_type": -1, "uid": "5548273173"}, {"original_text": "[思考]//@孔庆东:看你以后再敢得罪我们和尚！", "username": "夜逛族", "province": 44, "statuses_count": 4028, "friends_count": 330, "city": 1, "text": "[思考]", "user_description": "", "mid": "3845369425729691", "verified_reason": "", "followers_count": 83, "parent": "3845368045582125", "t": 1432290976, "gender": "m", "verified": false, "verified_type": -1, "uid": "5102154985"}, {"original_text": "[偷笑]//@孔庆东:看你以后再敢得罪我们和尚！", "username": "佩弦海军", "province": 100, "statuses_count": 239, "friends_count": 118, "city": 1000, "text": "[偷笑]", "user_description": "", "mid": "3845369710752147", "verified_reason": "", "followers_count": 11, "parent": "3845368045582125", "t": 1432291045, "gender": "m", "verified": false, "verified_type": -1, "uid": "3614519371"}, {"original_text": "转发微博", "username": "潇湘情中国心", "province": 43, "statuses_count": 16328, "friends_count": 1210, "city": 1, "text": "转发微博", "user_description": "潇湘情中国心", "mid": "3845370142855080", "verified_reason": "", "followers_count": 1141, "parent": "3845367072792129", "t": 1432291147, "gender": "m", "verified": false, "verified_type": -1, "uid": "1059579997"}, {"original_text": "庙里的大和尚和外来的山姆神父勾勾搭搭眉来眼去，你看不惯，当然要难为你了。 //@孔庆东:看你以后再敢得罪我们和尚！", "username": "慕容姑娘不戴花", "province": 100, "statuses_count": 6487, "friends_count": 111, "city": 1000, "text": "庙里的大和尚和外来的山姆神父勾勾搭搭眉来眼去，你看不惯，当然要难为你了。 ", "user_description": "", "mid": "3845370252001839", "verified_reason": "", "followers_count": 180, "parent": "3845368045582125", "t": 1432291173, "gender": "f", "verified": false, "verified_type": -1, "uid": "3920302373"}, {"original_text": "//@孔庆东:看你以后再敢得罪我们和尚！", "username": "岩礁58", "province": 11, "statuses_count": 56522, "friends_count": 811, "city": 1, "text": "", "user_description": "赖活着，只为尽孝道  只站对，不站队  反台独", "mid": "3845370532441288", "verified_reason": "", "followers_count": 1242, "parent": "3845368045582125", "t": 1432291241, "gender": "m", "verified": false, "verified_type": -1, "uid": "1218981057"}, {"original_text": "毛主席说，狗汉奸就在党内，狗汉奸就在党内的高层[嘻嘻][嘻嘻]//@孔庆东:看你以后再敢得罪我们和尚！", "username": "螺丝商城", "province": 13, "statuses_count": 568, "friends_count": 42, "city": 4, "text": "毛主席说，狗汉奸就在党内，狗汉奸就在党内的高层[嘻嘻][嘻嘻]", "user_description": "各种各样的螺丝在这里有卖啊！", "mid": "3845370658282764", "verified_reason": "", "followers_count": 81, "parent": "3845368045582125", "t": 1432291271, "gender": "m", "verified": false, "verified_type": -1, "uid": "1681843113"}, {"original_text": "转发微博", "username": "麦克raymond", "province": 22, "statuses_count": 3616, "friends_count": 1275, "city": 24, "text": "转发微博", "user_description": "天才并不是自生自长在深林荒野里的怪物，是由可以使天才生长的民众产生、长育出来的，所以没有这种民众，就没有天才。－－鲁迅", "mid": "3845371006444361", "verified_reason": "沈阳市沈河区和竹餐厅 销售代表", "followers_count": 129, "parent": "3845368045582125", "t": 1432291354, "gender": "m", "verified": true, "verified_type": 0, "uid": "5128386303"}, {"original_text": "大五毛司马夹头臭了吗？爱国臭了吗？[哆啦A梦微笑]", "username": "远东异端审问官", "province": 42, "statuses_count": 2178, "friends_count": 172, "city": 1, "text": "大五毛司马夹头臭了吗？爱国臭了吗？[哆啦A梦微笑]", "user_description": "宅腐双修。兔小将请自戕，自干五请自觉http://somalilandgov.com/ 非官方宣传。 “终有一天，人们想起了寻找小黄本时被墙的屈辱。”——进击的", "mid": "3845371027878352", "verified_reason": "", "followers_count": 82, "parent": "3845367072792129", "t": 1432291359, "gender": "m", "verified": false, "verified_type": -1, "uid": "2636473121"}, {"original_text": "//@孔庆东: 看你以后再敢得罪我们和尚！", "username": "汪汪和尚", "province": 31, "statuses_count": 9920, "friends_count": 496, "city": 1, "text": "", "user_description": "", "mid": "3845371027678082", "verified_reason": "", "followers_count": 353, "parent": "3845368045582125", "t": 1432291359, "gender": "m", "verified": false, "verified_type": -1, "uid": "1890302180"}, {"original_text": "//@孔庆东: 看你以后再敢得罪我们和尚！", "username": "我应无忧为何犹", "province": 13, "statuses_count": 27681, "friends_count": 117, "city": 8, "text": "", "user_description": "工人", "mid": "3845371115507093", "verified_reason": "", "followers_count": 281, "parent": "3845368045582125", "t": 1432291380, "gender": "m", "verified": false, "verified_type": -1, "uid": "2599636371"}, {"original_text": "原来是师太干的！//@孔庆东:看你以后再敢得罪我们和尚！", "username": "中国懵", "province": 400, "statuses_count": 94944, "friends_count": 2000, "city": 1000, "text": "原来是师太干的！", "user_description": "怒视一切奸佞小人和汉奸卖国贼！伟大光荣正确的毛泽东思想万岁！人民万岁！中国共产党万岁！坚持社会主义道路不动摇！", "mid": "3845371518525446", "verified_reason": "", "followers_count": 4734, "parent": "3845368045582125", "t": 1432291476, "gender": "m", "verified": false, "verified_type": -1, "uid": "1346261585"}, {"original_text": "握叉！我说怎么好多人不见露头了，显示关注396，点开刷新变成308", "username": "温情小木匠", "province": 13, "statuses_count": 340, "friends_count": 238, "city": 1, "text": "握叉！我说怎么好多人不见露头了，显示关注396，点开刷新变成308", "user_description": "无径之林，常有情趣，无人之岸，几多惊喜…吾爱世人，更爱自然…", "mid": "3845371673869204", "verified_reason": "", "followers_count": 106, "parent": "3845367072792129", "t": 1432291512, "gender": "m", "verified": false, "verified_type": -1, "uid": "3672243127"}, {"original_text": " //@孔庆东:看你以后再敢得罪我们和尚！", "username": "森林中的二只兔子", "province": 44, "statuses_count": 15126, "friends_count": 2806, "city": 1, "text": " ", "user_description": "广州十八载", "mid": "3845372147522257", "verified_reason": "", "followers_count": 384, "parent": "3845368045582125", "t": 1432291625, "gender": "m", "verified": false, "verified_type": -1, "uid": "2787567933"}, {"original_text": "吹牛逼的新方法啊！还真觉得自己是人物？", "username": "fzhoo", "province": 44, "statuses_count": 3296, "friends_count": 223, "city": 3, "text": "吹牛逼的新方法啊！还真觉得自己是人物？", "user_description": "俺不是实力派。。。。。。。", "mid": "3845372713435791", "verified_reason": "", "followers_count": 222, "parent": "3845367072792129", "t": 1432291761, "gender": "m", "verified": false, "verified_type": -1, "uid": "1910443354"}, {"original_text": "当新浪也被国民党接管了，此类事很正常吧！//@孔庆东: 看你以后再敢得罪我们和尚！", "username": "华南飞猛", "province": 44, "statuses_count": 21445, "friends_count": 1044, "city": 3, "text": "当新浪也被国民党接管了，此类事很正常吧！", "user_description": "", "mid": "3845372843876187", "verified_reason": "", "followers_count": 299, "parent": "3845368045582125", "t": 1432291791, "gender": "m", "verified": false, "verified_type": -1, "uid": "5349536344"}, {"original_text": "两个五毛，看过来！[拍照]咔咔[哈哈]//@孔庆东:看你以后再敢得罪我们和尚！", "username": "用户5610861441", "province": 33, "statuses_count": 34, "friends_count": 100, "city": 3, "text": "两个五毛，看过来！[拍照]咔咔[哈哈]", "user_description": "", "mid": "3845372907072998", "verified_reason": "", "followers_count": 3, "parent": "3845368045582125", "t": 1432291806, "gender": "m", "verified": false, "verified_type": -1, "uid": "5610861441"}, {"original_text": "新浪不仅稀饭你们俩，也稀饭我们这些支持你们的粉丝。我们跟你们是同样的待遇, 光见通知粉丝新增若干，就是不见粉丝数增加，反而时而有下降的时候. 俺们已经习以为常了都.//@孔庆东:看你以后再敢得罪我们和尚！", "username": "又见冰轮1", "province": 11, "statuses_count": 29298, "friends_count": 1905, "city": 1000, "text": "新浪不仅稀饭你们俩，也稀饭我们这些支持你们的粉丝。我们跟你们是同样的待遇, 光见通知粉丝新增若干，就是不见粉丝数增加，反而时而有下降的时候. 俺们已经习以为常了都.", "user_description": "又见冰轮又被新浪涅槃了一回，却始终没搞明白因为什么。俺想问：新浪，告诉俺你家大老板到底不喜欢听什么？给俺列个清单如何？", "mid": "3845372960829606", "verified_reason": "", "followers_count": 3047, "parent": "3845368045582125", "t": 1432291820, "gender": "f", "verified": false, "verified_type": -1, "uid": "3802666651"}, {"original_text": "大人物", "username": "明海老墨", "province": 11, "statuses_count": 26585, "friends_count": 379, "city": 8, "text": "大人物", "user_description": "支持自由、民主、法治、科学，反对宗教、中医、谣言、欺诈，坚持独立、客观", "mid": "3845373045348349", "verified_reason": "北京市京悦律师事务所高级合伙人", "followers_count": 4503, "parent": "3845367072792129", "t": 1432291839, "gender": "m", "verified": true, "verified_type": 0, "uid": "1163019635"}, {"original_text": "//@京悦-王少华律师: 大人物", "username": "光头的阿加西", "province": 44, "statuses_count": 60903, "friends_count": 888, "city": 1, "text": "", "user_description": "固废处理公众监督咨询委员会委员", "mid": "3845373213272357", "verified_reason": "", "followers_count": 2651, "parent": "3845373045348349", "t": 1432291879, "gender": "m", "verified": false, "verified_type": 220, "uid": "1666944534"}, {"original_text": "//@孔庆东: 看你以后再敢得罪我们和尚！", "username": "呼唤归来重生", "province": 37, "statuses_count": 15974, "friends_count": 199, "city": 1, "text": "", "user_description": "反台独", "mid": "3845373354872516", "verified_reason": "", "followers_count": 258, "parent": "3845368045582125", "t": 1432291914, "gender": "f", "verified": false, "verified_type": -1, "uid": "5025810914"}, {"original_text": "[哈哈]//@孔庆东:看你以后再敢得罪我们和尚！", "username": "洪维7775", "province": 51, "statuses_count": 4695, "friends_count": 251, "city": 1000, "text": "[哈哈]", "user_description": "", "mid": "3845374282749094", "verified_reason": "", "followers_count": 63, "parent": "3845368045582125", "t": 1432292135, "gender": "m", "verified": false, "verified_type": -1, "uid": "5390140117"}, {"original_text": "孟浩然：八月湖水平，涵虚混太清.气蒸云梦泽，波撼岳阳城.欲济无舟子，端居耻圣明.坐观垂钓者,徒有羡鱼情.--不如早回家，成全姜太公.", "username": "永乐大典丶", "province": 11, "statuses_count": 17416, "friends_count": 432, "city": 1, "text": "孟浩然：八月湖水平，涵虚混太清.气蒸云梦泽，波撼岳阳城.欲济无舟子，端居耻圣明.坐观垂钓者,徒有羡鱼情.--不如早回家，成全姜太公.", "user_description": "兴趣广泛，久经考验，物我两忘，心如水淡。人来人往皆为利,花开花落两由君。", "mid": "3845374706251772", "verified_reason": "", "followers_count": 333, "parent": "3845367072792129", "t": 1432292236, "gender": "m", "verified": false, "verified_type": -1, "uid": "5212475421"}, {"original_text": "司马，我帮你转！", "username": "简单和谐2011", "province": 32, "statuses_count": 1246, "friends_count": 115, "city": 10, "text": "司马，我帮你转！", "user_description": "", "mid": "3845375339443752", "verified_reason": "", "followers_count": 73, "parent": "3845367072792129", "t": 1432292387, "gender": "m", "verified": false, "verified_type": -1, "uid": "1402657552"}, {"original_text": "转发微博", "username": "piaodang5000nian", "province": 31, "statuses_count": 1132, "friends_count": 843, "city": 13, "text": "转发微博", "user_description": "", "mid": "3845376006302797", "verified_reason": "", "followers_count": 183, "parent": "3845367072792129", "t": 1432292546, "gender": "m", "verified": false, "verified_type": -1, "uid": "3211580627"}, {"original_text": "转发微博", "username": "minguo54年生人", "province": 45, "statuses_count": 4211, "friends_count": 324, "city": 3, "text": "转发微博", "user_description": "", "mid": "3845376518252948", "verified_reason": "", "followers_count": 71, "parent": "3845367072792129", "t": 1432292668, "gender": "m", "verified": false, "verified_type": -1, "uid": "3743662405"}, {"original_text": "//@孔庆东: 看你以后再敢得罪我们和尚！", "username": "蝉鸣时节胖十斤", "province": 34, "statuses_count": 4340, "friends_count": 341, "city": 1000, "text": "", "user_description": "事了拂衣去，深藏功与名__思密达~", "mid": "3845376727920019", "verified_reason": "", "followers_count": 44, "parent": "3845368045582125", "t": 1432292718, "gender": "m", "verified": false, "verified_type": -1, "uid": "5173058118"}, {"original_text": "你开评论粉丝就多了啊！", "username": "irsfly", "province": 32, "statuses_count": 593, "friends_count": 80, "city": 1000, "text": "你开评论粉丝就多了啊！", "user_description": "", "mid": "3845376878797102", "verified_reason": "", "followers_count": 32, "parent": "3845367072792129", "t": 1432292754, "gender": "m", "verified": false, "verified_type": -1, "uid": "1449983100"}, {"original_text": "一言不合就拉黑的竟然怀疑别人搞小动作涮他的粉[笑cry]", "username": "林建章67", "province": 61, "statuses_count": 6923, "friends_count": 763, "city": 1000, "text": "一言不合就拉黑的竟然怀疑别人搞小动作涮他的粉[笑cry]", "user_description": "", "mid": "3845381119048393", "verified_reason": "", "followers_count": 443, "parent": "3845367072792129", "t": 1432293765, "gender": "m", "verified": false, "verified_type": 220, "uid": "2259262013"}, {"original_text": "扑棱蛾子老说实话，良心大大滴好！ //@-_-熙望重来:→_→", "username": "梅铮星", "province": 11, "statuses_count": 45198, "friends_count": 1443, "city": 4, "text": "扑棱蛾子老说实话，良心大大滴好！ ", "user_description": "", "mid": "3845383781967830", "verified_reason": "", "followers_count": 4832, "parent": "3845383442676626", "t": 1432294400, "gender": "m", "verified": false, "verified_type": -1, "uid": "3667560763"}, {"original_text": "转发微博", "username": "凡宝移山", "province": 11, "statuses_count": 60956, "friends_count": 1991, "city": 1, "text": "转发微博", "user_description": "", "mid": "3845383845468425", "verified_reason": "", "followers_count": 1573, "parent": "3845367072792129", "t": 1432294415, "gender": "m", "verified": false, "verified_type": -1, "uid": "3275481613"}, {"original_text": "//@孔庆东:看你以后再敢得罪我们和尚！", "username": "yekai5002", "province": 32, "statuses_count": 14074, "friends_count": 83, "city": 6, "text": "", "user_description": "", "mid": "3845386852954176", "verified_reason": "", "followers_count": 56, "parent": "3845368045582125", "t": 1432295132, "gender": "m", "verified": false, "verified_type": -1, "uid": "2438393612"}, {"original_text": "转发微博", "username": "金公子来了", "province": 41, "statuses_count": 372, "friends_count": 88, "city": 1000, "text": "转发微博", "user_description": "", "mid": "3845387268338543", "verified_reason": "", "followers_count": 29, "parent": "3845367072792129", "t": 1432295231, "gender": "m", "verified": false, "verified_type": -1, "uid": "2945967537"}, {"original_text": "司马不是胡同串子！崔永元不是科学家！", "username": "李不宜", "province": 50, "statuses_count": 7561, "friends_count": 362, "city": 5, "text": "司马不是胡同串子！崔永元不是科学家！", "user_description": "机械设计工程师", "mid": "3845387410824628", "verified_reason": "", "followers_count": 420, "parent": "3845367072792129", "t": 1432295265, "gender": "m", "verified": false, "verified_type": -1, "uid": "1318085102"}, {"original_text": "//@中国懵:原来是师太干的！//@孔庆东:看你以后再敢得罪我们和尚！", "username": "红星闪闪YZH", "province": 44, "statuses_count": 23438, "friends_count": 3144, "city": 6, "text": "", "user_description": "江苏苏州人，人在广东佛山。", "mid": "3845388404818336", "verified_reason": "", "followers_count": 4049, "parent": "3845371518525446", "t": 1432295502, "gender": "m", "verified": false, "verified_type": -1, "uid": "1597207322"}, {"original_text": "司马南还是坚持认为自己很重要，似乎认为自己能够左右地球自西向东还是自东向西转似的。\"薄帅\"已经进秦城了，康师傅也快开庭了，司马南为什么还会有这种幻觉呢？[笑cry]", "username": "小白兔爱啃骨头", "province": 100, "statuses_count": 8306, "friends_count": 301, "city": 1000, "text": "司马南还是坚持认为自己很重要，似乎认为自己能够左右地球自西向东还是自东向西转似的。\"薄帅\"已经进秦城了，康师傅也快开庭了，司马南为什么还会有这种幻觉呢？[笑cry]", "user_description": "", "mid": "3845388492824910", "verified_reason": "", "followers_count": 979, "parent": "3845367072792129", "t": 1432295523, "gender": "f", "verified": false, "verified_type": -1, "uid": "2793701147"}, {"original_text": "转发微博", "username": "kikifu32c", "province": 11, "statuses_count": 50457, "friends_count": 1982, "city": 1, "text": "转发微博", "user_description": "", "mid": "3845390103638096", "verified_reason": "", "followers_count": 1908, "parent": "3845367072792129", "t": 1432295907, "gender": "m", "verified": false, "verified_type": -1, "uid": "3682470103"}, {"original_text": "傻逼真不少", "username": "十一楼_王猛", "province": 23, "statuses_count": 5539, "friends_count": 723, "city": 2, "text": "傻逼真不少", "user_description": "优质东北大米移植基地！", "mid": "3845391244267558", "verified_reason": "", "followers_count": 220, "parent": "3845367072792129", "t": 1432296179, "gender": "m", "verified": false, "verified_type": -1, "uid": "81272407"}, {"original_text": "//@kikifu32c:转发微博", "username": "NMY多杰才旦", "province": 63, "statuses_count": 6467, "friends_count": 541, "city": 1000, "text": "", "user_description": "毛主席的好战士。", "mid": "3845391852540957", "verified_reason": "", "followers_count": 313, "parent": "3845390103638096", "t": 1432296323, "gender": "m", "verified": false, "verified_type": -1, "uid": "2252736032"}, {"original_text": "你以为你抖的小聪明别人看不透", "username": "静水深流3490921733", "province": 13, "statuses_count": 374, "friends_count": 247, "city": 1, "text": "你以为你抖的小聪明别人看不透", "user_description": "", "mid": "3845395685890114", "verified_reason": "", "followers_count": 34, "parent": "3845367072792129", "t": 1432297238, "gender": "m", "verified": false, "verified_type": -1, "uid": "3490921733"}, {"original_text": "转发微博", "username": "夜漫漫6422", "province": 23, "statuses_count": 2454, "friends_count": 596, "city": 1000, "text": "转发微博", "user_description": "崇尚公平正义，拥护毛泽东思想，拥护社会主义道路，反对剥削制度，反对一切“牛、鬼、蛇、神”。", "mid": "3845396634228578", "verified_reason": "", "followers_count": 404, "parent": "3845367072792129", "t": 1432297464, "gender": "m", "verified": false, "verified_type": -1, "uid": "1807705691"}, {"original_text": "转发微博", "username": "shixin", "province": 33, "statuses_count": 9552, "friends_count": 174, "city": 1, "text": "转发微博", "user_description": "", "mid": "3845397481131003", "verified_reason": "", "followers_count": 46, "parent": "3845367072792129", "t": 1432297666, "gender": "m", "verified": false, "verified_type": -1, "uid": "1423354364"}, {"original_text": "我也很久没看到司马大叔更新微博了。//@孔庆东:看你以后再敢得罪我们和尚！", "username": "普洱玫瑰汤", "province": 31, "statuses_count": 4122, "friends_count": 286, "city": 1, "text": "我也很久没看到司马大叔更新微博了。", "user_description": "在混沌的世界中寻找前进的明灯。", "mid": "3845398244398653", "verified_reason": "", "followers_count": 194, "parent": "3845368045582125", "t": 1432297848, "gender": "f", "verified": false, "verified_type": -1, "uid": "2938373997"}, {"original_text": "就知道 当我不能在司马老师微博评论的时候 我就知道", "username": "2另11", "province": 11, "statuses_count": 685, "friends_count": 17, "city": 1000, "text": "就知道 当我不能在司马老师微博评论的时候 我就知道", "user_description": "喝过一卡车酒  读过两卡车书", "mid": "3845404246486430", "verified_reason": "", "followers_count": 45, "parent": "3845367072792129", "t": 1432299279, "gender": "m", "verified": false, "verified_type": -1, "uid": "1950037350"}, {"original_text": "//@孔庆东:看你以后再敢得罪我们和尚！", "username": "沉默启明", "province": 44, "statuses_count": 3129, "friends_count": 197, "city": 6, "text": "", "user_description": "唤醒工农千百万 还我庄严静土", "mid": "3845406415009151", "verified_reason": "", "followers_count": 190, "parent": "3845368045582125", "t": 1432299796, "gender": "m", "verified": false, "verified_type": -1, "uid": "3486108494"}, {"original_text": "修正：是9万多，不是9千多[嘻嘻]//@情系丹江:没注意你原有多少粉，我只看到@千钧客 原有11万多粉，现在掉到9千多粉，不知浪浪搞什么鬼？！", "username": "情系丹江", "province": 41, "statuses_count": 32060, "friends_count": 553, "city": 1, "text": "修正：是9万多，不是9千多[嘻嘻]", "user_description": "领导我们事业的核心力量是中国共产党，指导我们思想的理论基础是马列主义毛泽东思想！", "mid": "3845407010550721", "verified_reason": "河南南阳宛淅凌岗凌氏宗族理事会 秘书长、谱书主编凌建学", "followers_count": 3352, "parent": "3845368519643444", "t": 1432299938, "gender": "m", "verified": true, "verified_type": 0, "uid": "3118531003"}, {"original_text": "[吐]//@阿里公鸡: //@小白兔爱啃骨头:司马南还是坚持认为自己很重要，似乎认为自己能够左右地球自西向东还是自东向西转似的。\"薄帅\"已经进秦城了，康师傅也快开庭了，司马南为什么还会有这种幻觉呢？[笑cry]", "username": "荷兰通讯", "province": 400, "statuses_count": 34816, "friends_count": 375, "city": 22, "text": "[吐]", "user_description": "我们从历史中得到的唯一教训是，从来没有人汲取历史教训。——黑格尔", "mid": "3845410747936417", "verified_reason": "", "followers_count": 1999, "parent": "3845408587066899", "t": 1432300829, "gender": "m", "verified": false, "verified_type": -1, "uid": "2232232030"}, {"original_text": "转发微博", "username": "用户3896304770", "province": 100, "statuses_count": 462, "friends_count": 40, "city": 1000, "text": "转发微博", "user_description": "", "mid": "3845416208825107", "verified_reason": "", "followers_count": 10, "parent": "3845367072792129", "t": 1432302131, "gender": "m", "verified": false, "verified_type": -1, "uid": "3896304770"}, {"original_text": "转基因司马南以为自己是个人物。@林治波 @孔庆东 //@阿里公鸡: //@小白兔爱啃骨头:司马南还是坚持认为自己很重要，似乎认为自己能够左右地球自西向东还是自东向西转似的。\"薄帅\"已经进秦城了，康师傅也快开庭了，司马南为什", "username": "往事919", "province": 53, "statuses_count": 25632, "friends_count": 1189, "city": 1000, "text": "转基因司马南以为自己是个人物。@林治波 @孔庆东 ", "user_description": "爱国、爱民、爱家，痛恨一切汉奸卖国贼。", "mid": "3845418439949470", "verified_reason": "", "followers_count": 1450, "parent": "3845408587066899", "t": 1432302662, "gender": "m", "verified": false, "verified_type": -1, "uid": "1408001185"}, {"original_text": "司马南不转基因还是好人//@孔庆东: 看你以后再敢得罪我们和尚！", "username": "海口老周", "province": 46, "statuses_count": 9875, "friends_count": 69, "city": 1, "text": "司马南不转基因还是好人", "user_description": "", "mid": "3845418549296440", "verified_reason": "", "followers_count": 108, "parent": "3845368045582125", "t": 1432302688, "gender": "m", "verified": false, "verified_type": -1, "uid": "1224615327"}, {"original_text": "不止如此，我多次尝试回复您的微博却没有一次成功。", "username": "埃姆维皮", "province": 44, "statuses_count": 216, "friends_count": 143, "city": 3, "text": "不止如此，我多次尝试回复您的微博却没有一次成功。", "user_description": "健康是一切的基础", "mid": "3845419865915587", "verified_reason": "", "followers_count": 37, "parent": "3845367072792129", "t": 1432303003, "gender": "m", "verified": false, "verified_type": -1, "uid": "1251617937"}, {"original_text": "没事不扯淡。多想做做学问", "username": "田恒娃子", "province": 42, "statuses_count": 691, "friends_count": 170, "city": 1, "text": "没事不扯淡。多想做做学问", "user_description": "有计划地做事情，有目的地交朋友。", "mid": "3845421258094299", "verified_reason": "", "followers_count": 114, "parent": "3845367072792129", "t": 1432303335, "gender": "m", "verified": false, "verified_type": -1, "uid": "5181746436"}, {"original_text": "@司马南，你想忽悠让民众还相信你的#爱国生意#吗？说说你的#美国别墅#和#爱国生意#如何？【http://t.cn/RAEfFK8】 【http://t.cn/R2b1nt3", "username": "山高水长1115", "province": 11, "statuses_count": 20824, "friends_count": 512, "city": 1000, "text": "@司马南，你想忽悠让民众还相信你的#爱国生意#吗？说说你的#美国别墅#和#爱国生意#如何？【http://t.cn/RAEfFK8】 【http://t.cn/R2b1nt3", "user_description": "仁者无敌，揭露一个虚假民主自由的美国，为毛泽东思想而战斗不息！反转才是真爱国！", "mid": "3845422714134546", "verified_reason": "", "followers_count": 2045, "parent": "3845418595353022", "t": 1432303682, "gender": "m", "verified": false, "verified_type": 220, "uid": "3811702975"}, {"original_text": "右边请看清这个做#爱国生意#的！薄入狱就变脸的投机分子！ //@南岩春y:你就烧高香吧？@郭松民 原来有一百多万粉，你现在去看看还有多少//@孔庆东: 看你以后再敢得罪我们和尚！", "username": "山高水长1115", "province": 11, "statuses_count": 20824, "friends_count": 512, "city": 1000, "text": "右边请看清这个做#爱国生意#的！薄入狱就变脸的投机分子！ ", "user_description": "仁者无敌，揭露一个虚假民主自由的美国，为毛泽东思想而战斗不息！反转才是真爱国！", "mid": "3845423163122287", "verified_reason": "", "followers_count": 2045, "parent": "3845418595353022", "t": 1432303789, "gender": "m", "verified": false, "verified_type": 220, "uid": "3811702975"}, {"original_text": "夹头没脸懒得骂了。", "username": "最烦看广告", "province": 100, "statuses_count": 9814, "friends_count": 995, "city": 1000, "text": "夹头没脸懒得骂了。", "user_description": "能吃会做", "mid": "3845426450832005", "verified_reason": "", "followers_count": 987, "parent": "3845367072792129", "t": 1432304573, "gender": "m", "verified": false, "verified_type": -1, "uid": "2912790903"}, {"original_text": "封杀您的人真是气量小，不自信了，让人鄙视！其实也不用封杀您，很多微博都是在自证嘛[偷笑]", "username": "鼬稚", "province": 37, "statuses_count": 8504, "friends_count": 147, "city": 13, "text": "封杀您的人真是气量小，不自信了，让人鄙视！其实也不用封杀您，很多微博都是在自证嘛[偷笑]", "user_description": "", "mid": "3845427939745899", "verified_reason": "", "followers_count": 92, "parent": "3845367072792129", "t": 1432304928, "gender": "m", "verified": false, "verified_type": -1, "uid": "3052667547"}, {"original_text": "//@孔庆东:看你以后再敢得罪我们和尚！", "username": "健坤强德之声闻", "province": 36, "statuses_count": 40087, "friends_count": 867, "city": 1000, "text": "", "user_description": "“健坤强德”微博于去年被腥狼残忍莫名而注销之，而博客之名亦被篡改为‘健坤强德_bZg’，只能阅读和转载，隐忍一年余，搬家到此，开始博客新生！", "mid": "3845430876065664", "verified_reason": "", "followers_count": 774, "parent": "3845368045582125", "t": 1432305628, "gender": "m", "verified": false, "verified_type": -1, "uid": "3958344200"}, {"original_text": "转发微博", "username": "司马平邦", "province": 11, "statuses_count": 60493, "friends_count": 2818, "city": 1, "text": "转发微博", "user_description": "自由自在自然。", "mid": "3845431479991419", "verified_reason": "著名时政、影视评论人；天农网CEO；中国名博沙龙常务副主席。", "followers_count": 605970, "parent": "3845367072792129", "t": 1432305771, "gender": "m", "verified": true, "verified_type": 0, "uid": "1400887105"}, {"original_text": "//@司马平邦:转发微博", "username": "行云天马", "province": 32, "statuses_count": 3260, "friends_count": 261, "city": 1000, "text": "", "user_description": "", "mid": "3845431823439749", "verified_reason": "", "followers_count": 133, "parent": "3845431479991419", "t": 1432305853, "gender": "m", "verified": false, "verified_type": -1, "uid": "1455542262"}, {"original_text": "言论自由是你们的眼中钉，被审查应该谢主隆恩啊！ //@司马平邦:转发微博", "username": "luise92", "province": 11, "statuses_count": 7420, "friends_count": 1575, "city": 14, "text": "言论自由是你们的眼中钉，被审查应该谢主隆恩啊！ ", "user_description": "活在现实里的理想主义者。", "mid": "3845432084478833", "verified_reason": "", "followers_count": 781, "parent": "3845431479991419", "t": 1432305915, "gender": "m", "verified": false, "verified_type": 220, "uid": "2415809382"}, {"original_text": "//@行云天马: //@司马平邦:转发微博", "username": "华夏-执著", "province": 100, "statuses_count": 25440, "friends_count": 1990, "city": 1000, "text": "", "user_description": "", "mid": "3845432474588268", "verified_reason": "", "followers_count": 1165, "parent": "3845431823439749", "t": 1432306008, "gender": "m", "verified": false, "verified_type": -1, "uid": "1050608741"}, {"original_text": "//@司马平邦: 转发微博", "username": "爱国愤青微博", "province": 21, "statuses_count": 14155, "friends_count": 588, "city": 1000, "text": "", "user_description": "", "mid": "3845432856245821", "verified_reason": "", "followers_count": 1351, "parent": "3845431479991419", "t": 1432306099, "gender": "m", "verified": false, "verified_type": 220, "uid": "1390714690"}, {"original_text": "觉得确有一种神秘的力量在控制着中国的网络舆论，无孔不入，无所不在地处处拆共产党的台。或明火执杖，或旁敲侧击，或指桑骂槐，或故弄玄虚，或煽风点火……//@司马平邦:转发微博", "username": "山人萧让", "province": 23, "statuses_count": 2879, "friends_count": 688, "city": 1, "text": "觉得确有一种神秘的力量在控制着中国的网络舆论，无孔不入，无所不在地处处拆共产党的台。或明火执杖，或旁敲侧击，或指桑骂槐，或故弄玄虚，或煽风点火……", "user_description": "作品：《鲁迅滚蛋了，他笔下的人物欢呼雀跃了》入选2009中国年度杂文", "mid": "3845434952946063", "verified_reason": "", "followers_count": 2702, "parent": "3845431479991419", "t": 1432306600, "gender": "m", "verified": false, "verified_type": -1, "uid": "2667998413"}, {"original_text": "有对薄公堂的意思", "username": "寒山草茶青", "province": 37, "statuses_count": 8954, "friends_count": 419, "city": 6, "text": "有对薄公堂的意思", "user_description": "", "mid": "3845436291361768", "verified_reason": "", "followers_count": 336, "parent": "3845367072792129", "t": 1432306919, "gender": "m", "verified": false, "verified_type": -1, "uid": "2706895111"}, {"original_text": "//@司马平邦:转发微博", "username": "cycp1945", "province": 11, "statuses_count": 7676, "friends_count": 221, "city": 8, "text": "", "user_description": "", "mid": "3845436437327629", "verified_reason": "", "followers_count": 212, "parent": "3845431479991419", "t": 1432306954, "gender": "m", "verified": false, "verified_type": -1, "uid": "1932841197"}, {"original_text": "天天想限制别人的这群人，就应该被剥夺一切发言权力，直接发配到金胖子那。 //@司马平邦:转发微博", "username": "JUN风言风语", "province": 43, "statuses_count": 1301, "friends_count": 207, "city": 1, "text": "天天想限制别人的这群人，就应该被剥夺一切发言权力，直接发配到金胖子那。 ", "user_description": "", "mid": "3845439180558681", "verified_reason": "", "followers_count": 39, "parent": "3845431479991419", "t": 1432307607, "gender": "m", "verified": false, "verified_type": -1, "uid": "3837247310"}, {"original_text": "司马不是胡同串子！崔永元不是科学家！", "username": "笑看风云淡9063", "province": 37, "statuses_count": 1469, "friends_count": 162, "city": 10, "text": "司马不是胡同串子！崔永元不是科学家！", "user_description": "善良，但不能软弱；恃才，也不要放旷 。面对邪恶，我不想沉默！", "mid": "3845440594525234", "verified_reason": "", "followers_count": 49, "parent": "3845367072792129", "t": 1432307945, "gender": "m", "verified": false, "verified_type": -1, "uid": "5339585468"}, {"original_text": "淡然处之。", "username": "把酒起舞清风", "province": 14, "statuses_count": 3934, "friends_count": 469, "city": 5, "text": "淡然处之。", "user_description": "", "mid": "3845440677865520", "verified_reason": "", "followers_count": 257, "parent": "3845367072792129", "t": 1432307965, "gender": "m", "verified": false, "verified_type": -1, "uid": "1449742661"}, {"original_text": "进去的节奏！", "username": "麦田守望翁2", "province": 11, "statuses_count": 11168, "friends_count": 696, "city": 8, "text": "进去的节奏！", "user_description": "只有在开水里，茶叶才能展开生命浓郁的香气", "mid": "3845442758698447", "verified_reason": "", "followers_count": 5472, "parent": "3845367072792129", "t": 1432308461, "gender": "m", "verified": false, "verified_type": -1, "uid": "5227110273"}, {"original_text": "还好，我还能看到您", "username": "-水龙头-", "province": 11, "statuses_count": 1402, "friends_count": 73, "city": 1000, "text": "还好，我还能看到您", "user_description": "", "mid": "3845444075214395", "verified_reason": "", "followers_count": 86, "parent": "3845367072792129", "t": 1432308775, "gender": "m", "verified": false, "verified_type": -1, "uid": "2326866441"}, {"original_text": "前朝余孽", "username": "一生爱绿", "province": 14, "statuses_count": 12555, "friends_count": 680, "city": 10, "text": "前朝余孽", "user_description": "文盲", "mid": "3845446089111428", "verified_reason": "", "followers_count": 316, "parent": "3845367072792129", "t": 1432309255, "gender": "m", "verified": false, "verified_type": -1, "uid": "1296563580"}, {"original_text": "司马先生不必气馁...", "username": "一米夜光", "province": 46, "statuses_count": 1318, "friends_count": 53, "city": 1, "text": "司马先生不必气馁...", "user_description": "我只想了解和传播方舟子先生的理念。", "mid": "3845450270516692", "verified_reason": "", "followers_count": 53, "parent": "3845367072792129", "t": 1432310252, "gender": "m", "verified": false, "verified_type": -1, "uid": "1885589300"}, {"original_text": "太有才了。支持司马！", "username": "水手与浪", "province": 100, "statuses_count": 1808, "friends_count": 101, "city": 1000, "text": "太有才了。支持司马！", "user_description": "梦开始的地方，洒满月光......", "mid": "3845451314779021", "verified_reason": "", "followers_count": 87, "parent": "3845367072792129", "t": 1432310500, "gender": "m", "verified": false, "verified_type": -1, "uid": "1624367094"}, {"original_text": "转发微博", "username": "热爱生活和祖国", "province": 12, "statuses_count": 634, "friends_count": 392, "city": 4, "text": "转发微博", "user_description": "低调的奢华", "mid": "3845453822677880", "verified_reason": "前 天津淘题网络科技有限公司 创始人", "followers_count": 535, "parent": "3845367072792129", "t": 1432311099, "gender": "m", "verified": true, "verified_type": 0, "uid": "2730378867"}, {"original_text": "转发微博", "username": "上图老保安", "province": 31, "statuses_count": 41871, "friends_count": 556, "city": 1000, "text": "转发微博", "user_description": "", "mid": "3845456432106547", "verified_reason": "", "followers_count": 201, "parent": "3845367072792129", "t": 1432311721, "gender": "m", "verified": false, "verified_type": -1, "uid": "1859494613"}, {"original_text": "被渣浪盯上了啊，谁叫您是名人啊，裤衩又红。", "username": "汉宣定胡2014", "province": 35, "statuses_count": 884, "friends_count": 132, "city": 8, "text": "被渣浪盯上了啊，谁叫您是名人啊，裤衩又红。", "user_description": "攻城狮，标准自干五。", "mid": "3845458990333617", "verified_reason": "", "followers_count": 36, "parent": "3845367072792129", "t": 1432312331, "gender": "m", "verified": false, "verified_type": -1, "uid": "3160096404"}, {"original_text": "//@司马平邦: 转发微博", "username": "神秘的何在", "province": 31, "statuses_count": 21749, "friends_count": 71, "city": 1000, "text": "", "user_description": "", "mid": "3845459150265027", "verified_reason": "", "followers_count": 118, "parent": "3845431479991419", "t": 1432312368, "gender": "m", "verified": false, "verified_type": -1, "uid": "3349775532"}, {"original_text": "转发微博", "username": "中华儿女2_2", "province": 14, "statuses_count": 36372, "friends_count": 1463, "city": 1, "text": "转发微博", "user_description": "", "mid": "3845460844101805", "verified_reason": "", "followers_count": 882, "parent": "3845367072792129", "t": 1432312773, "gender": "m", "verified": false, "verified_type": -1, "uid": "3748188542"}, {"original_text": "转发微博", "username": "刘渊加油", "province": 44, "statuses_count": 868, "friends_count": 213, "city": 3, "text": "转发微博", "user_description": "本人基本观点：1、相信奥派经济学相信市场力量，2、相信科学反对中医反对传统文化，3、赞同全盘西化实行宪政，反独裁反专政，反蒋反毛。", "mid": "3845478532130000", "verified_reason": "", "followers_count": 174, "parent": "3845367072792129", "t": 1432316990, "gender": "m", "verified": false, "verified_type": -1, "uid": "2183212461"}, {"original_text": "不是胡同串子，是被主人抛弃的乏五毛", "username": "刘渊加油", "province": 44, "statuses_count": 868, "friends_count": 213, "city": 3, "text": "不是胡同串子，是被主人抛弃的乏五毛", "user_description": "本人基本观点：1、相信奥派经济学相信市场力量，2、相信科学反对中医反对传统文化，3、赞同全盘西化实行宪政，反独裁反专政，反蒋反毛。", "mid": "3845479207405699", "verified_reason": "", "followers_count": 174, "parent": "3845367072792129", "t": 1432317151, "gender": "m", "verified": false, "verified_type": -1, "uid": "2183212461"}, {"original_text": "Repost", "username": "yuweiwu_oqi", "province": 400, "statuses_count": 3496, "friends_count": 46, "city": 1, "text": "Repost", "user_description": "", "mid": "3845480100843138", "verified_reason": "", "followers_count": 54, "parent": "3845367072792129", "t": 1432317364, "gender": "f", "verified": false, "verified_type": -1, "uid": "1336571442"}, {"original_text": "//@小白兔爱啃骨头:司马南还是坚持认为自己很重要，似乎认为自己能够左右地球自西向东还是自东向西转似的。\"薄帅\"已经进秦城了，康师傅也快开庭了，司马南为什么还会有这种幻觉呢？[笑cry]", "username": "吕氏讲堂", "province": 11, "statuses_count": 5379, "friends_count": 182, "city": 1000, "text": "", "user_description": "这是讲解商业模式和管理智慧的讲堂。欢迎交流。有些参考材料和预备知识可以在本人博客上找到。", "mid": "3845498240907642", "verified_reason": "中科院研究生院教授", "followers_count": 2990632, "parent": "3845388492824910", "t": 1432321689, "gender": "m", "verified": true, "verified_type": 0, "uid": "1223208794"}, {"original_text": "[哈哈] @司马南 知足吧，毛泽东诗曰：“牢骚太盛防肠断。”众所周知，你练过扯蛋功，将新浪网霸刘索拉都肏出肺癌了，通奸刘志丹侄女罪孽啊，红色皇宫禁脔不能乱吃啊[哈哈]刘索拉是摇滚歌手，在你屌中摇滚，用生命去叫春，过猛而癌，你的蛋是否爽毙了？[哈哈]粤语：有咁风流，就有咁折堕。[哈哈][哈哈]", "username": "常定居士钟怀京6", "province": 44, "statuses_count": 15322, "friends_count": 32, "city": 1000, "text": "[哈哈] @司马南 知足吧，毛泽东诗曰：“牢骚太盛防肠断。”众所周知，你练过扯蛋功，将新浪网霸刘索拉都肏出肺癌了，通奸刘志丹侄女罪孽啊，红色皇宫禁脔不能乱吃啊[哈哈]刘索拉是摇滚歌手，在你屌中摇滚，用生命去叫春，过猛而癌，你的蛋是否爽毙了？[哈哈]粤语：有咁风流，就有咁折堕。[哈哈][哈哈]", "user_description": "", "mid": "3845508999392352", "verified_reason": "", "followers_count": 620, "parent": "3845488732789920", "t": 1432324254, "gender": "m", "verified": false, "verified_type": -1, "uid": "2623039753"}, {"original_text": "//@司马平邦:转发微博", "username": "无尘随缘", "province": 11, "statuses_count": 16845, "friends_count": 271, "city": 5, "text": "", "user_description": "", "mid": "3845549147479016", "verified_reason": "", "followers_count": 180, "parent": "3845431479991419", "t": 1432333826, "gender": "m", "verified": false, "verified_type": -1, "uid": "1536857355"}, {"original_text": "你的微博怎么不能评论呢？", "username": "倒转天宇解悬李民", "province": 32, "statuses_count": 1150, "friends_count": 79, "city": 3, "text": "你的微博怎么不能评论呢？", "user_description": "展社会弊政，谈天论地。", "mid": "3845559347629653", "verified_reason": "", "followers_count": 138, "parent": "3845367072792129", "t": 1432336258, "gender": "m", "verified": false, "verified_type": -1, "uid": "2971182024"}, {"original_text": "转发微博", "username": "qq造化鸟", "province": 33, "statuses_count": 6570, "friends_count": 281, "city": 2, "text": "转发微博", "user_description": "【反台独】", "mid": "3845561357028776", "verified_reason": "", "followers_count": 203, "parent": "3845367072792129", "t": 1432336736, "gender": "f", "verified": false, "verified_type": -1, "uid": "1321679650"}, {"original_text": " //@孔庆东:看你以后再敢得罪我们和尚！", "username": "北京农家饭", "province": 11, "statuses_count": 12444, "friends_count": 367, "city": 2, "text": " ", "user_description": "老农", "mid": "3845563164235292", "verified_reason": "", "followers_count": 553, "parent": "3845368045582125", "t": 1432337168, "gender": "m", "verified": false, "verified_type": 220, "uid": "2207499693"}, {"original_text": "//@山高水长1115: @司马南，你想忽悠让民众还相信你的#爱国生意#吗？说说你的#美国别墅#和#爱国生意#如何？【 http://t.cn/RAEfFK8 】 【 http://t.cn/R2b1nt3", "username": "杯心映月", "province": 14, "statuses_count": 4045, "friends_count": 1831, "city": 4, "text": "", "user_description": "樽前放歌月中眠", "mid": "3845573574335782", "verified_reason": "", "followers_count": 4020, "parent": "3845422714134546", "t": 1432339649, "gender": "m", "verified": false, "verified_type": -1, "uid": "5070660280"}, {"original_text": "投机客嘴脸早已暴露，必遭各方抛弃，看起来，司马已没有未来了[衰]", "username": "骑着乌龟上路123456789", "province": 100, "statuses_count": 1619, "friends_count": 321, "city": 1000, "text": "投机客嘴脸早已暴露，必遭各方抛弃，看起来，司马已没有未来了[衰]", "user_description": "", "mid": "3845584756526483", "verified_reason": "", "followers_count": 58, "parent": "3845367072792129", "t": 1432342316, "gender": "m", "verified": false, "verified_type": -1, "uid": "1468971710"}, {"original_text": "👍 @司马南 知足吧，毛泽东诗曰：“牢骚太盛防肠断。”众所周知，你练过扯蛋功，将新浪网霸刘索拉都肏出肺癌了，通奸刘志丹侄女罪孽啊，红色皇宫禁脔不能乱吃啊[哈哈]刘索拉是摇滚歌手，在你屌中摇滚，用生命去叫春，过猛而癌，你的蛋是否爽毙了？[哈哈]粤语：有咁风流，就有咁折堕。[哈哈][哈哈]", "username": "安全地带多昵咪", "province": 44, "statuses_count": 1878, "friends_count": 559, "city": 1, "text": "👍 @司马南 知足吧，毛泽东诗曰：“牢骚太盛防肠断。”众所周知，你练过扯蛋功，将新浪网霸刘索拉都肏出肺癌了，通奸刘志丹侄女罪孽啊，红色皇宫禁脔不能乱吃啊[哈哈]刘索拉是摇滚歌手，在你屌中摇滚，用生命去叫春，过猛而癌，你的蛋是否爽毙了？[哈哈]粤语：有咁风流，就有咁折堕。[哈哈][哈哈]", "user_description": "人只可以活一次，你又点甘心退而求次. 🈶好嘅嘢至值得擁有，如果唔係倒不如一🈚️所有。", "mid": "3845594638597611", "verified_reason": "", "followers_count": 230, "parent": "3845508999392352", "t": 1432344672, "gender": "m", "verified": false, "verified_type": -1, "uid": "2740187707"}, {"original_text": "👍@常定居士钟怀京6 @司马南 知足吧，毛泽东诗曰：“牢骚太盛防肠断。”你练过扯蛋功，将刘索拉都肏出肺癌了，通奸刘志丹侄女罪孽啊，红色皇宫禁脔不能乱吃啊[哈哈]刘索拉是摇滚歌手，在你屌中摇滚，用生命去叫春，过猛而癌，你的蛋是否爽毙了？[哈哈]粤语：有咁风流，就有咁折堕。[哈哈][哈哈]", "username": "安全地带多昵咪", "province": 44, "statuses_count": 1878, "friends_count": 559, "city": 1, "text": "👍@常定居士钟怀京6 @司马南 知足吧，毛泽东诗曰：“牢骚太盛防肠断。”你练过扯蛋功，将刘索拉都肏出肺癌了，通奸刘志丹侄女罪孽啊，红色皇宫禁脔不能乱吃啊[哈哈]刘索拉是摇滚歌手，在你屌中摇滚，用生命去叫春，过猛而癌，你的蛋是否爽毙了？[哈哈]粤语：有咁风流，就有咁折堕。[哈哈][哈哈]", "user_description": "人只可以活一次，你又点甘心退而求次. 🈶好嘅嘢至值得擁有，如果唔係倒不如一🈚️所有。", "mid": "3845595276137976", "verified_reason": "", "followers_count": 230, "parent": "3845594638597611", "t": 1432344824, "gender": "m", "verified": false, "verified_type": -1, "uid": "2740187707"}, {"original_text": "草尼马@微博管理员 一大早六七条微博发送失败  挖根😡睡在背后鬼七王八的 //@司马平邦:转发微博", "username": "坐山观虎斗法", "province": 54, "statuses_count": 1774, "friends_count": 69, "city": 1, "text": "草尼马@微博管理员 一大早六七条微博发送失败  挖根😡睡在背后鬼七王八的 ", "user_description": "天行健君子自强不息", "mid": "3845615409063249", "verified_reason": "", "followers_count": 48, "parent": "3845431479991419", "t": 1432349624, "gender": "m", "verified": false, "verified_type": -1, "uid": "3392237562"}, {"original_text": "转发微博", "username": "方岩论剑", "province": 33, "statuses_count": 2912, "friends_count": 331, "city": 7, "text": "转发微博", "user_description": "有朋自远方来，不亦乐乎！", "mid": "3845644416522252", "verified_reason": "", "followers_count": 63, "parent": "3845367072792129", "t": 1432356540, "gender": "m", "verified": false, "verified_type": -1, "uid": "3720907025"}, {"original_text": "有关方面。。。", "username": "丛中笑K", "province": 35, "statuses_count": 387, "friends_count": 49, "city": 3, "text": "有关方面。。。", "user_description": "", "mid": "3845651303900572", "verified_reason": "", "followers_count": 5, "parent": "3845367072792129", "t": 1432358182, "gender": "m", "verified": false, "verified_type": -1, "uid": "3007965834"}, {"original_text": "Cnmb为啥不能评论？还说自己掉粉。@司马南 ", "username": "新微评论", "province": 31, "statuses_count": 11, "friends_count": 15, "city": 15, "text": "Cnmb为啥不能评论？还说自己掉粉。@司马南 ", "user_description": "", "mid": "3845652784543702", "verified_reason": "", "followers_count": 3, "parent": "3845367072792129", "t": 1432358535, "gender": "m", "verified": false, "verified_type": -1, "uid": "1410474480"}, {"original_text": "新浪也好，腾讯也好，都早已这样做了。不过现在更厉害了。网络之控猛于虎也。", "username": "戴旭粉丝团", "province": 31, "statuses_count": 4466, "friends_count": 2000, "city": 1000, "text": "新浪也好，腾讯也好，都早已这样做了。不过现在更厉害了。网络之控猛于虎也。", "user_description": "针对时弊，观点独特。经过企业黄埔培训、西点培训。毛泽东思想深入研究者。时政评论者。常收听粉丝会经常更换置前……", "mid": "3845688821059182", "verified_reason": "", "followers_count": 5685, "parent": "3845367072792129", "t": 1432367127, "gender": "m", "verified": false, "verified_type": -1, "uid": "2011786093"}, {"original_text": "转发微博", "username": "行者无崖365", "province": 42, "statuses_count": 10980, "friends_count": 262, "city": 1, "text": "转发微博", "user_description": "多难未必兴邦，多演必定穿帮！", "mid": "3845780194768041", "verified_reason": "", "followers_count": 120, "parent": "3845367072792129", "t": 1432388912, "gender": "m", "verified": false, "verified_type": -1, "uid": "2683079583"}, {"original_text": "没有问题。但要相信，铁杆粉丝怎么掉，都能找到您，除非新浪倒闭。[哈哈]", "username": "秦岭兵甲", "province": 11, "statuses_count": 2534, "friends_count": 367, "city": 1, "text": "没有问题。但要相信，铁杆粉丝怎么掉，都能找到您，除非新浪倒闭。[哈哈]", "user_description": "我是一个兵，来自老百姓。", "mid": "3845988723142721", "verified_reason": "", "followers_count": 185, "parent": "3845367072792129", "t": 1432438629, "gender": "m", "verified": false, "verified_type": -1, "uid": "3559422085"}, {"original_text": "转发微博", "username": "中华儿女2_2", "province": 14, "statuses_count": 36372, "friends_count": 1463, "city": 1, "text": "转发微博", "user_description": "", "mid": "3845988894430283", "verified_reason": "", "followers_count": 882, "parent": "3845367072792129", "t": 1432438670, "gender": "m", "verified": false, "verified_type": -1, "uid": "3748188542"}, {"original_text": "//@孔庆东: 看你以后再敢得罪我们和尚！", "username": "中华儿女2_2", "province": 14, "statuses_count": 36372, "friends_count": 1463, "city": 1, "text": "", "user_description": "", "mid": "3845992837225873", "verified_reason": "", "followers_count": 882, "parent": "3845368045582125", "t": 1432439609, "gender": "m", "verified": false, "verified_type": -1, "uid": "3748188542"}, {"original_text": "//@孔庆东:看你以后再敢得罪我们和尚！", "username": "绿妖无智", "province": 14, "statuses_count": 42942, "friends_count": 1998, "city": 1, "text": "", "user_description": "“自反而不缩，虽褐宽博，吾不惴焉？自反而缩，虽千万人，吾往矣。”", "mid": "3846059346802380", "verified_reason": "", "followers_count": 2522, "parent": "3845368045582125", "t": 1432455466, "gender": "m", "verified": false, "verified_type": -1, "uid": "1723683544"}, {"original_text": "[嘻嘻]", "username": "劳动者花七", "province": 31, "statuses_count": 23937, "friends_count": 906, "city": 1000, "text": "[嘻嘻]", "user_description": "每个人出生的时侯都是原创，可悲的是很多人渐渐都成了盗版。", "mid": "3846065096779161", "verified_reason": "", "followers_count": 1748, "parent": "3846059346802380", "t": 1432456838, "gender": "f", "verified": false, "verified_type": -1, "uid": "2611451627"}, {"original_text": " //@孔庆东:看你以后再敢得罪我们和尚！", "username": "夜客Yeke", "province": 33, "statuses_count": 185945, "friends_count": 4544, "city": 1000, "text": " ", "user_description": "对于在维护祖国之利益的过程中迸发出来的聪明智慧始终感兴趣", "mid": "3846196051834405", "verified_reason": "", "followers_count": 4443, "parent": "3845368045582125", "t": 1432488060, "gender": "m", "verified": false, "verified_type": -1, "uid": "2159290653"}, {"original_text": "哈哈，一怀疑你们相互炒作，二怀疑你们相互损毁对方，以致粉丝减少。//@孔庆东: 看你以后再敢得罪我们和尚！", "username": "顶薄之人", "province": 32, "statuses_count": 586, "friends_count": 13, "city": 2, "text": "哈哈，一怀疑你们相互炒作，二怀疑你们相互损毁对方，以致粉丝减少。", "user_description": "", "mid": "3846376939457755", "verified_reason": "", "followers_count": 22, "parent": "3845368045582125", "t": 1432531187, "gender": "m", "verified": false, "verified_type": -1, "uid": "3660918353"}, {"original_text": "夹头，你挺转的贴子发不出吗？继续演 //@新豪哥之冷锋南下://@夜客Yeke: //@孔庆东:看你以后再敢得罪我们和尚！", "username": "东方老邪", "province": 37, "statuses_count": 8405, "friends_count": 1684, "city": 1, "text": "夹头，你挺转的贴子发不出吗？继续演 ", "user_description": "", "mid": "3846386967655800", "verified_reason": "", "followers_count": 2492, "parent": "3846196919729482", "t": 1432533577, "gender": "m", "verified": false, "verified_type": -1, "uid": "2705830451"}, {"original_text": "//@新豪哥之冷锋南下: //@夜客Yeke: //@孔庆东:看你以后再敢得罪我们和尚！", "username": "北极春天阳光1", "province": 31, "statuses_count": 35836, "friends_count": 951, "city": 15, "text": "", "user_description": "东博书院http://www.dongboshuyuan.com/portal.php", "mid": "3846532141160630", "verified_reason": "", "followers_count": 784, "parent": "3846196919729482", "t": 1432568189, "gender": "m", "verified": false, "verified_type": -1, "uid": "3272311911"}, {"original_text": "//@戴旭粉丝团:新浪也好，腾讯也好，都早已这样做了。不过现在更厉害了。网络之控猛于虎也。", "username": "毛派必胜16", "province": 32, "statuses_count": 11626, "friends_count": 2165, "city": 12, "text": "", "user_description": "48岁，毛粉，薄粉。", "mid": "3846751918415490", "verified_reason": "", "followers_count": 3592, "parent": "3845688821059182", "t": 1432620589, "gender": "m", "verified": false, "verified_type": -1, "uid": "5397630613"}, {"original_text": "转发微博", "username": "薛懿翀", "province": 21, "statuses_count": 266, "friends_count": 107, "city": 5, "text": "转发微博", "user_description": "微博认证：儿童，其实我只是个小孩纸", "mid": "3849751277843510", "verified_reason": "", "followers_count": 10, "parent": "3845367072792129", "t": 1433335692, "gender": "f", "verified": false, "verified_type": -1, "uid": "5450418414"}, {"original_text": "//@西红柿了个番茄蛋:转发微博", "username": "薛懿翀", "province": 21, "statuses_count": 266, "friends_count": 107, "city": 5, "text": "", "user_description": "微博认证：儿童，其实我只是个小孩纸", "mid": "3908422888420440", "verified_reason": "", "followers_count": 10, "parent": "3849751277843510", "t": 1447324094, "gender": "f", "verified": false, "verified_type": -1, "uid": "5450418414"}]